Workbook

Sheet Job Costing
A1: JOB COSTING TRACKER
A3: Instructions: Enter job details in BLUE cells. All calculations update automatically.
A5: Job ID | B5: Customer Name | C5: Service Type | D5: Job Date | E5: Labor Hours | F5: Labor Rate ($/hr) | G5: Labor Cost | H5: Material Cost | I5: Job Revenue | J5: Gross Margin $ | K5: Gross Margin %
G6: =IF(AND(E6<>"",F6<>""),E6*F6,"") | J6: =IF(I6<>"",I6-(G6+H6),"") | K6: =IF(AND(I6<>"",J6<>""),J6/I6,"")
G7: =IF(AND(E7<>"",F7<>""),E7*F7,"") | J7: =IF(I7<>"",I7-(G7+H7),"") | K7: =IF(AND(I7<>"",J7<>""),J7/I7,"")
G8: =IF(AND(E8<>"",F8<>""),E8*F8,"") | J8: =IF(I8<>"",I8-(G8+H8),"") | K8: =IF(AND(I8<>"",J8<>""),J8/I8,"")
G9: =IF(AND(E9<>"",F9<>""),E9*F9,"") | J9: =IF(I9<>"",I9-(G9+H9),"") | K9: =IF(AND(I9<>"",J9<>""),J9/I9,"")
G10: =IF(AND(E10<>"",F10<>""),E10*F10,"") | J10: =IF(I10<>"",I10-(G10+H10),"") | K10: =IF(AND(I10<>"",J10<>""),J10/I10,"")
G11: =IF(AND(E11<>"",F11<>""),E11*F11,"") | J11: =IF(I11<>"",I11-(G11+H11),"") | K11: =IF(AND(I11<>"",J11<>""),J11/I11,"")
G12: =IF(AND(E12<>"",F12<>""),E12*F12,"") | J12: =IF(I12<>"",I12-(G12+H12),"") | K12: =IF(AND(I12<>"",J12<>""),J12/I12,"")
G13: =IF(AND(E13<>"",F13<>""),E13*F13,"") | J13: =IF(I13<>"",I13-(G13+H13),"") | K13: =IF(AND(I13<>"",J13<>""),J13/I13,"")
G14: =IF(AND(E14<>"",F14<>""),E14*F14,"") | J14: =IF(I14<>"",I14-(G14+H14),"") | K14: =IF(AND(I14<>"",J14<>""),J14/I14,"")
G15: =IF(AND(E15<>"",F15<>""),E15*F15,"") | J15: =IF(I15<>"",I15-(G15+H15),"") | K15: =IF(AND(I15<>"",J15<>""),J15/I15,"")
A18: MONTHLY SUMMARY
A19: Total Jobs Completed: | B19: =COUNTA(A6:A15) -> 0
A20: Total Revenue: | B20: =SUM(I6:I15) -> 0
A21: Total Labor Cost: | B21: =SUM(G6:G15) -> 0
A22: Total Material Cost: | B22: =SUM(H6:H15) -> 0
A23: Total Labor Hours: | B23: =SUM(E6:E15) -> 0
A24: Total Gross Margin $: | B24: =SUM(J6:J15) -> 0
A25: Average Gross Margin %: | B25: =IF(B20<>0,B24/B20,"")
A26: Avg Revenue per Job: | B26: =IF(B19<>0,B20/B19,"")
A27: Avg Labor Cost per Job: | B27: =IF(B19<>0,B21/B19,"")

Sheet Customer Tracker
A1: CUSTOMER LIFETIME VALUE TRACKER
A3: Instructions: Enter customer data in BLUE cells. Repeat rate and LTV calculate automatically.
A5: Customer ID | B5: Customer Name | C5: Acquisition Date | D5: Total Jobs | E5: Total Revenue (LTV) | F5: Last Service Date | G5: Repeat Customer? | H5: Days Since Service
G6: =IF(D6>1,"Yes",IF(D6=1,"No","")) | H6: =IF(F6<>"",TODAY()-F6,"")
G7: =IF(D7>1,"Yes",IF(D7=1,"No","")) | H7: =IF(F7<>"",TODAY()-F7,"")
G8: =IF(D8>1,"Yes",IF(D8=1,"No","")) | H8: =IF(F8<>"",TODAY()-F8,"")
G9: =IF(D9>1,"Yes",IF(D9=1,"No","")) | H9: =IF(F9<>"",TODAY()-F9,"")
G10: =IF(D10>1,"Yes",IF(D10=1,"No","")) | H10: =IF(F10<>"",TODAY()-F10,"")
G11: =IF(D11>1,"Yes",IF(D11=1,"No","")) | H11: =IF(F11<>"",TODAY()-F11,"")
G12: =IF(D12>1,"Yes",IF(D12=1,"No","")) | H12: =IF(F12<>"",TODAY()-F12,"")
G13: =IF(D13>1,"Yes",IF(D13=1,"No","")) | H13: =IF(F13<>"",TODAY()-F13,"")
G14: =IF(D14>1,"Yes",IF(D14=1,"No","")) | H14: =IF(F14<>"",TODAY()-F14,"")
G15: =IF(D15>1,"Yes",IF(D15=1,"No","")) | H15: =IF(F15<>"",TODAY()-F15,"")
G16: =IF(D16>1,"Yes",IF(D16=1,"No","")) | H16: =IF(F16<>"",TODAY()-F16,"")
G17: =IF(D17>1,"Yes",IF(D17=1,"No","")) | H17: =IF(F17<>"",TODAY()-F17,"")
... G25: =IF(D25>1,"Yes",IF(D25=1,"No","")) | H25: =IF(F25<>"",TODAY()-F25,"")
A28: CUSTOMER METRICS SUMMARY
A29: Total Customers Tracked: | B29: =COUNTA(A6:A25) -> 0
A30: Repeat Customers: | B30: =COUNTIF(G6:G25,"Yes") -> 0
A31: Repeat Customer Rate: | B31: =IF(B29<>0,B30/B29,"")
A32: Total Revenue (All Customers): | B32: =SUM(E6:E25) -> 0
A33: Average Customer LTV: | B33: =IF(B29<>0,B32/B29,"")
A34: Average Jobs per Customer: | B34: =IF(B29<>0,SUM(D6:D25)/B29,"")
A35: Repeat Customer LTV: | B35: =IFERROR(AVERAGEIF(G6:G25,"Yes",E6:E25),"-") -> -
A36: Single-Purchase Customer LTV: | B36: =IFERROR(AVERAGEIF(G6:G25,"No",E6:E25),"-") -> -

Sheet Pricing Master
A1: PRICING & PRODUCT MASTER
A3: Instructions: Define all service packages, products, and pricing tiers here.
A5: Product/Service | B5: Category | C5: Supplier | D5: Cost (COGS) | E5: List Price | F5: Markup % | G5: Unit | H5: Status
A6: Boiler Installation - Standard | B6: Boiler | C6: WCI | D6: 1200 | E6: 3500 | F6: =IF(AND(D6<>"",E6<>""),IF(D6=0,"N/A",(E6-D6)/D6),"N/A") -> 1.9166667 | G6: Each | H6: Active
A7: Boiler Installation - Premium | B7: Boiler | C7: WCI | D7: 1800 | E7: 5000 | F7: =IF(AND(D7<>"",E7<>""),IF(D7=0,"N/A",(E7-D7)/D7),"N/A") -> 1.7777778 | G7: Each | H7: Active
A8: Service Call - Diagnostic | B8: Service | C8: Internal | D8: 0 | E8: 150 | F8: =IF(AND(D8<>"",E8<>""),IF(D8=0,"N/A",(E8-D8)/D8),"N/A") -> N/A | G8: Call | H8: Active
A9: Service Call - Repair | B9: Service | C9: Internal | D9: 0 | E9: 250 | F9: =IF(AND(D9<>"",E9<>""),IF(D9=0,"N/A",(E9-D9)/D9),"N/A") -> N/A | G9: Call | H9: Active
A10: Annual Maintenance Contract | B10: Service | C10: Internal | D10: 0 | E10: 500 | F10: =IF(AND(D10<>"",E10<>""),IF(D10=0,"N/A",(E10-D10)/D10),"N/A") -> N/A | G10: Year | H10: Active
A11: Solar Installation - 5kW | B11: Solar | C11: Solartech | D11: 4500 | E11: 12000 | F11: =IF(AND(D11<>"",E11<>""),IF(D11=0,"N/A",(E11-D11)/D11),"N/A") -> 1.6666667 | G11: Each | H11: Active
A12: Solar Installation - 10kW | B12: Solar | C12: Solartech | D12: 8500 | E12: 22000 | F12: =IF(AND(D12<>"",E12<>""),IF(D12=0,"N/A",(E12-D12)/D12),"N/A") -> 1.5882353 | G12: Each | H12: Active
A13: Solar Monitoring Service | B13: Solar | C13: Internal | D13: 0 | E13: 100 | F13: =IF(AND(D13<>"",E13<>""),IF(D13=0,"N/A",(E13-D13)/D13),"N/A") -> N/A | G13: Month | H13: Active
A14: Water Heater Replacement | B14: Water | C14: WCI | D14: 800 | E14: 2200 | F14: =IF(AND(D14<>"",E14<>""),IF(D14=0,"N/A",(E14-D14)/D14),"N/A") -> 1.75 | G14: Each | H14: Active
A15: Emergency After-Hours Call | B15: Service | C15: Internal | D15: 0 | E15: 400 | F15: =IF(AND(D15<>"",E15<>""),IF(D15=0,"N/A",(E15-D15)/D15),"N/A") -> N/A | G15: Call | H15: Active
A18: PRICING STRATEGY & ASSUMPTIONS
A20: Standard Labor Rate ($/hour):
A21: Service Call Markup Target:
A22: Product Markup Target:
A23: Minimum Job Gross Margin %:

Sheet Pipeline & Leads
A1: SALES PIPELINE & LEADS TRACKER
A3: Instructions: Enter lead and opportunity data in BLUE cells. Pipeline value calculates automatically.
A5: Lead ID | B5: Lead Name | C5: Lead Source | D5: Service Interest | E5: Status | F5: Estimated Value | G5: Probability % | H5: Weighted Value | I5: Days in Pipeline
H6: =IF(AND(F6<>"",G6<>""),F6*G6,"")
H7: =IF(AND(F7<>"",G7<>""),F7*G7,"")
H8: =IF(AND(F8<>"",G8<>""),F8*G8,"")
H9: =IF(AND(F9<>"",G9<>""),F9*G9,"")
H10: =IF(AND(F10<>"",G10<>""),F10*G10,"")
H11: =IF(AND(F11<>"",G11<>""),F11*G11,"")
H12: =IF(AND(F12<>"",G12<>""),F12*G12,"")
H13: =IF(AND(F13<>"",G13<>""),F13*G13,"")
H14: =IF(AND(F14<>"",G14<>""),F14*G14,"")
H15: =IF(AND(F15<>"",G15<>""),F15*G15,"")
H16: =IF(AND(F16<>"",G16<>""),F16*G16,"")
H17: =IF(AND(F17<>"",G17<>""),F17*G17,"")
... H20: =IF(AND(F20<>"",G20<>""),F20*G20,"")
A23: PIPELINE SUMMARY
A24: Total Leads: | B24: =COUNTA(A6:A20) -> 0
A25: Total Pipeline Value (Unweighted): | B25: =SUM(F6:F20) -> 0
A26: Total Weighted Pipeline Value: | B26: =SUM(H6:H20) -> 0
A27: Average Deal Value: | B27: =IF(B24<>0,B25/B24,"")
A28: Average Probability: | B28: =IF(B24<>0,AVERAGE(G6:G20),"")
A29: Average Days in Pipeline: | B29: =IF(B24<>0,AVERAGE(I6:I20),"")

Sheet Monthly KPIs
A1: HIPPOS - MONTHLY KPI DASHBOARD
A2: Report Month:
A4: KEY ASSUMPTIONS
A5: Customer Acquisition Cost (CAC):
A6: Avg Labor Cost per Hour:
A7: Target Gross Margin %:
A8: Total Monthly Overhead ($):
A11: REVENUE METRICS
A12: Total Revenue: | B12: ='Job Costing'!B20 -> 0
A13: Revenue from New Customers:
A14: Revenue from Repeat Customers:
A15: Repeat Revenue %: | B15: =IF(B12<>0,B14/B12,"")
A16: Average Revenue per Job: | B16: ='Job Costing'!B26
A17: Revenue per Technician:
A20: PROFITABILITY METRICS
A21: Gross Profit: | B21: ='Job Costing'!B24 -> 0
A22: Gross Margin %: | B22: =IF(B12<>0,B21/B12,"")
A23: Total Labor Cost: | B23: ='Job Costing'!B21 -> 0
A24: Labor Cost % of Revenue: | B24: =IF(B12<>0,B23/B12,"")
A25: Total Material Cost: | B25: ='Job Costing'!B22 -> 0
A26: Material Cost % of Revenue: | B26: =IF(B12<>0,B25/B12,"")
A27: Operating Profit (before overhead): | B27: =B21 -> 0
A28: Net Profit (after overhead): | B28: =B21-B8 -> 0
A29: Net Margin %: | B29: =IF(B12<>0,B28/B12,"")
A32: CUSTOMER METRICS
A33: New Customers Acquired:
A34: Repeat Customers: | B34: ='Customer Tracker'!B30 -> 0
A35: Repeat Customer Rate: | B35: ='Customer Tracker'!B31
A36: Total Customers (active):
A37: Average Customer LTV: | B37: ='Customer Tracker'!B33
A38: Customer Acquisition Cost (CAC): | B38: =B5 -> 0
A39: LTV:CAC Ratio: | B39: =IF(B38<>0,B37/B38,"")
A40: Payback Period (months): | B40: =IFERROR(IF(AND(B37<>0,B37>0),B38/(B37/12),""),"")
A43: OPERATIONAL METRICS
A44: Total Jobs Completed: | B44: ='Job Costing'!B19 -> 0
A45: Total Labor Hours: | B45: ='Job Costing'!B23 -> 0
A46: Avg Labor Cost per Job: | B46: ='Job Costing'!B27
A47: First-Time Fix Rate:
A48: On-Time Completion Rate:
A49: Customer Satisfaction (NPS):
