Workbook

Sheet _RAW_Deals
A1: Paste Zoho export here (starting at A2)
A2: Deal ID | B2: Deal Name | C2: Account ID | D2: Account Name | E2: Deal Amount | F2: Stage | G2: Probability %

Sheet _RAW_Invoices
A1: Paste Zoho export here (starting at A2)
A2: Invoice ID | B2: Product Category | C2: Product Name | D2: Quantity | E2: Line Total ($)

Sheet _RAW_Stock
A1: Paste Zoho export here (starting at A2)
A2: Product ID | B2: Product Name | C2: Category | D2: Qty on Hand | E2: Unit Cost ($) | F2: Inventory Value ($) | G2: Reorder Level

Sheet _RAW_PO
A1: Paste Zoho export here (starting at A2)
A2: PO ID | B2: Product Name | C2: Quantity | D2: Total Cost ($)

Sheet _RAW_SO
A1: Paste Zoho export here (starting at A2)
A2: Order ID | B2: Customer Name | C2: Is Intercompany | D2: Order Total ($)

Sheet Settings
A1: SETTINGS & ASSUMPTIONS
A2: Monthly COGS (for DIO calculation): | B2: 0
A3: Currency: | B3: USD
A4: Fiscal Year Start Month: | B4: 1
A5: Report Generated: | B5: 2026-01-31

Sheet Pipeline Tracker
A1: SOLARTECH PIPELINE TRACKER
A2: Paste Zoho CRM Deals export into _RAW_Deals sheet, then refresh this analysis
A4: Stage | B4: Deal Count | C4: Total Value ($) | D4: Avg Deal Size ($) | E4: Min Deal ($) | F4: Max Deal ($) | G4: Probability Avg (%) | H4: Forecast ($)
A5: Prospect | B5: =COUNTIF(_RAW_Deals!F:F,"Prospect") -> 0 | C5: =SUMIF(_RAW_Deals!F:F,"Prospect",_RAW_Deals!E:E) -> 0 | D5: =IFERROR(C5/B5,0) -> 0 | E5: =IFERROR(minifs(_RAW_Deals!E:E,_RAW_Deals!F:F,"Prospect"),"-") -> - | F5: =IFERROR(maxifs(_RAW_Deals!E:E,_RAW_Deals!F:F,"Prospect"),"-") -> - | G5: =IFERROR(AVERAGEIF(_RAW_Deals!F:F,"Prospect",_RAW_Deals!G:G),0) -> 0 | H5: =IFERROR(C5*(G5/100),0) -> 0
A6: Qualification | B6: =COUNTIF(_RAW_Deals!F:F,"Qualification") -> 0 | C6: =SUMIF(_RAW_Deals!F:F,"Qualification",_RAW_Deals!E:E) -> 0 | D6: =IFERROR(C6/B6,0) -> 0 | E6: =IFERROR(minifs(_RAW_Deals!E:E,_RAW_Deals!F:F,"Qualification"),"-") -> - | F6: =IFERROR(maxifs(_RAW_Deals!E:E,_RAW_Deals!F:F,"Qualification"),"-") -> - | G6: =IFERROR(AVERAGEIF(_RAW_Deals!F:F,"Qualification",_RAW_Deals!G:G),0) -> 0 | H6: =IFERROR(C6*(G6/100),0) -> 0
A7: Proposal | B7: =COUNTIF(_RAW_Deals!F:F,"Proposal") -> 0 | C7: =SUMIF(_RAW_Deals!F:F,"Proposal",_RAW_Deals!E:E) -> 0 | D7: =IFERROR(C7/B7,0) -> 0 | E7: =IFERROR(minifs(_RAW_Deals!E:E,_RAW_Deals!F:F,"Proposal"),"-") -> - | F7: =IFERROR(maxifs(_RAW_Deals!E:E,_RAW_Deals!F:F,"Proposal"),"-") -> - | G7: =IFERROR(AVERAGEIF(_RAW_Deals!F:F,"Proposal",_RAW_Deals!G:G),0) -> 0 | H7: =IFERROR(C7*(G7/100),0) -> 0
A8: Negotiation | B8: =COUNTIF(_RAW_Deals!F:F,"Negotiation") -> 0 | C8: =SUMIF(_RAW_Deals!F:F,"Negotiation",_RAW_Deals!E:E) -> 0 | D8: =IFERROR(C8/B8,0) -> 0 | E8: =IFERROR(minifs(_RAW_Deals!E:E,_RAW_Deals!F:F,"Negotiation"),"-") -> - | F8: =IFERROR(maxifs(_RAW_Deals!E:E,_RAW_Deals!F:F,"Negotiation"),"-") -> - | G8: =IFERROR(AVERAGEIF(_RAW_Deals!F:F,"Negotiation",_RAW_Deals!G:G),0) -> 0 | H8: =IFERROR(C8*(G8/100),0) -> 0
A9: Closed Won | B9: =COUNTIF(_RAW_Deals!F:F,"Closed Won") -> 0 | C9: =SUMIF(_RAW_Deals!F:F,"Closed Won",_RAW_Deals!E:E) -> 0 | D9: =IFERROR(C9/B9,0) -> 0 | E9: =IFERROR(minifs(_RAW_Deals!E:E,_RAW_Deals!F:F,"Closed Won"),"-") -> - | F9: =IFERROR(maxifs(_RAW_Deals!E:E,_RAW_Deals!F:F,"Closed Won"),"-") -> - | G9: =IFERROR(AVERAGEIF(_RAW_Deals!F:F,"Closed Won",_RAW_Deals!G:G),0) -> 0 | H9: =IFERROR(C9*(G9/100),0) -> 0
A10: Closed Lost | B10: =COUNTIF(_RAW_Deals!F:F,"Closed Lost") -> 0 | C10: =SUMIF(_RAW_Deals!F:F,"Closed Lost",_RAW_Deals!E:E) -> 0 | D10: =IFERROR(C10/B10,0) -> 0 | E10: =IFERROR(minifs(_RAW_Deals!E:E,_RAW_Deals!F:F,"Closed Lost"),"-") -> - | F10: =IFERROR(maxifs(_RAW_Deals!E:E,_RAW_Deals!F:F,"Closed Lost"),"-") -> - | G10: =IFERROR(AVERAGEIF(_RAW_Deals!F:F,"Closed Lost",_RAW_Deals!G:G),0) -> 0 | H10: =IFERROR(C10*(G10/100),0) -> 0
A12: SUMMARY METRICS | B12: Open Pipeline | C12: Total Pipeline | D12: Win Rate %
A13: Values: | B13: =SUM(C5:C8) -> 0 | C13: =SUM(C5:C11) -> 0 | D13: =IFERROR(C10/(C10+C11),0) -> 0

Sheet Margin Analysis
A1: MARGIN ANALYSIS
A2: Paste Zoho Invoices and Stock data to calculate margins by product line
A4: Product Category | B4: Total Revenue ($) | C4: Total COGS ($) | D4: Gross Profit ($) | E4: Gross Margin %
A5: Solar | B5: =SUMIF(_RAW_Invoices!B:B,"Solar",_RAW_Invoices!E:E) -> 0 | C5: =SUMIF(_RAW_Stock!C:C,"Solar",_RAW_Stock!F:F) -> 0 | D5: =B5-C5 -> 0 | E5: =IFERROR(D5/B5,0) -> 0
A6: Boiler | B6: =SUMIF(_RAW_Invoices!B:B,"Boiler",_RAW_Invoices!E:E) -> 0 | C6: =SUMIF(_RAW_Stock!C:C,"Boiler",_RAW_Stock!F:F) -> 0 | D6: =B6-C6 -> 0 | E6: =IFERROR(D6/B6,0) -> 0
A7: Water Treatment | B7: =SUMIF(_RAW_Invoices!B:B,"Water Treatment",_RAW_Invoices!E:E) -> 0 | C7: =SUMIF(_RAW_Stock!C:C,"Water Treatment",_RAW_Stock!F:F) -> 0 | D7: =B7-C7 -> 0 | E7: =IFERROR(D7/B7,0) -> 0
A8: TOTAL | B8: =SUM(B5:B7) -> 0 | C8: =SUM(C5:C7) -> 0 | D8: =B8-C8 -> 0 | E8: =IFERROR(D8/B8,0) -> 0
A11: Top Customers | B11: Revenue ($) | C11: COGS ($) | D11: Gross Profit ($) | E11: Margin %

Sheet Inventory Status
A1: INVENTORY STATUS
A2: Paste Zoho Inventory Stock data to analyze inventory health
A4: Product Category | B4: Qty on Hand | C4: Inventory Value ($) | D4: Reorder Level | E4: Days Inventory | F4: Status
A5: Solar | B5: =SUMIF(_RAW_Stock!C:C,"Solar",_RAW_Stock!D:D) -> 0 | C5: =SUMIF(_RAW_Stock!C:C,"Solar",_RAW_Stock!F:F) -> 0 | D5: =SUMIF(_RAW_Stock!C:C,"Solar",_RAW_Stock!G:G) -> 0 | E5: =IFERROR((C5/Settings!$B$2)/30,0) -> 0 | F5: =IF(B5<D5,"REORDER",IF(E5>90,"SLOW","OK")) -> OK
A6: Boiler | B6: =SUMIF(_RAW_Stock!C:C,"Boiler",_RAW_Stock!D:D) -> 0 | C6: =SUMIF(_RAW_Stock!C:C,"Boiler",_RAW_Stock!F:F) -> 0 | D6: =SUMIF(_RAW_Stock!C:C,"Boiler",_RAW_Stock!G:G) -> 0 | E6: =IFERROR((C6/Settings!$B$2)/30,0) -> 0 | F6: =IF(B6<D6,"REORDER",IF(E6>90,"SLOW","OK")) -> OK
A7: Water Treatment | B7: =SUMIF(_RAW_Stock!C:C,"Water Treatment",_RAW_Stock!D:D) -> 0 | C7: =SUMIF(_RAW_Stock!C:C,"Water Treatment",_RAW_Stock!F:F) -> 0 | D7: =SUMIF(_RAW_Stock!C:C,"Water Treatment",_RAW_Stock!G:G) -> 0 | E7: =IFERROR((C7/Settings!$B$2)/30,0) -> 0 | F7: =IF(B7<D7,"REORDER",IF(E7>90,"SLOW","OK")) -> OK
A8: TOTAL | B8: =SUM(B5:B7) -> 0 | C8: =SUM(C5:C7) -> 0
A11: Product Name | B11: Days in Stock | C11: Qty on Hand | D11: Action
A12: [Auto-populated from raw data - sort by Days > 90]

Sheet Intercompany Tracking
A1: INTERCOMPANY TRANSACTIONS
A2: Track purchases from WCI (supplier) and sales to Hippos (retail arm)
A4: Month | B4: PO Count | C4: Total Spend ($) | D4: Avg PO Value ($) | E4: Top Product
A5: Jan | B5: [Count from PO data]
A6: Feb | B6: [Count from PO data]
A7: Mar | B7: [Count from PO data]
A8: Apr | B8: [Count from PO data]
A9: May | B9: [Count from PO data]
A10: Jun | B10: [Count from PO data]
A11: Jul | B11: [Count from PO data]
A12: Aug | B12: [Count from PO data]
A13: Sep | B13: [Count from PO data]
A14: Oct | B14: [Count from PO data]
A15: Nov | B15: [Count from PO data]
A16: Dec | B16: [Count from PO data]
A19: Month | B19: Order Count | C19: Revenue ($) | D19: Avg Order Value ($) | E19: Top Product
A20: Jan | B20: [Count from SO data]
A21: Feb | B21: [Count from SO data]
A22: Mar | B22: [Count from SO data]
A23: Apr | B23: [Count from SO data]
A24: May | B24: [Count from SO data]
A25: Jun | B25: [Count from SO data]
A26: Jul | B26: [Count from SO data]
A27: Aug | B27: [Count from SO data]
A28: Sep | B28: [Count from SO data]
A29: Oct | B29: [Count from SO data]
A30: Nov | B30: [Count from SO data]
A31: Dec | B31: [Count from SO data]
A34: Product | B34: WCI Cost ($) | C34: Solartech Price ($) | D34: Hippos Price ($) | E34: Total Markup %
A35: Solar Panel - 400W | B35: 0 | C35: 0 | D35: 0 | E35: =IFERROR((D35-C35)/C35,0) -> 0
A36: Boiler - 100L | B36: 0 | C36: 0 | D36: 0 | E36: =IFERROR((D36-C36)/C36,0) -> 0
A37: Water Filter - Pro | B37: 0 | C37: 0 | D37: 0 | E37: =IFERROR((D37-C37)/C37,0) -> 0

Sheet Monthly KPIs
A1: MONTHLY KPI SUMMARY
A2: Select Month/Year: | B2: January 2026
A4: Metric | B4: Current Month | C4: Prior Month | D4: YTD Target
A5: Total Revenue ($) | B5: 0 | C5: 0 | D5: 0
A6: Gross Profit ($) | B6: 0 | C6: 0 | D6: 0
A7: Gross Margin % | B7: 0 | C7: 0 | D7: 0
A8: Pipeline Value ($) | B8: 0 | C8: 0 | D8: 0
A9: Deals Closed Won | B9: 0 | C9: 0 | D9: 0
A10: Win Rate % | B10: 0 | C10: 0 | D10: 0
A11: Inventory Value ($) | B11: 0 | C11: 0 | D11: 0
A12: Inventory Turnover (days) | B12: 0 | C12: 0 | D12: 0
A13: Order Fulfillment Rate % | B13: 0 | C13: 0 | D13: 0
A14: Average Deal Size ($) | B14: 0 | C14: 0 | D14: 0
A15: Days Sales Outstanding | B15: 0 | C15: 0 | D15: 0
A16: Customer Count | B16: 0 | C16: 0 | D16: 0
