Workbook

Sheet Trade Journal
A1: TRADING JOURNAL
A2: Learn first, systematize later. Log every trade.
A3: Blue cells = Input | Black = Calculated
A5: Date | B5: Time | C5: Symbol | D5: Direction | E5: Entry Price | F5: Exit Price | G5: Qty | H5: Position Size | I5: Gross P&L | J5: Fees | K5: Net P&L | L5: R-Multiple | M5: Win/Loss | N5: Setup | O5: Thesis | P5: What Happened | Q5: Lesson | R5: Grade
H6: =IF(E6="","",E6*G6) | I6: =IF(OR(E6="",F6=""),"",IF(D6="Long",(F6-E6)*G6,(E6-F6)*G6)) | K6: =IF(I6="","",I6-J6) | L6: =IF(K6="","",K6/H6*100) | M6: =IF(K6="","",IF(K6>0,"WIN",IF(K6<0,"LOSS","EVEN")))
H7: =IF(E7="","",E7*G7) | I7: =IF(OR(E7="",F7=""),"",IF(D7="Long",(F7-E7)*G7,(E7-F7)*G7)) | K7: =IF(I7="","",I7-J7) | L7: =IF(K7="","",K7/H7*100) | M7: =IF(K7="","",IF(K7>0,"WIN",IF(K7<0,"LOSS","EVEN")))
H8: =IF(E8="","",E8*G8) | I8: =IF(OR(E8="",F8=""),"",IF(D8="Long",(F8-E8)*G8,(E8-F8)*G8)) | K8: =IF(I8="","",I8-J8) | L8: =IF(K8="","",K8/H8*100) | M8: =IF(K8="","",IF(K8>0,"WIN",IF(K8<0,"LOSS","EVEN")))
H9: =IF(E9="","",E9*G9) | I9: =IF(OR(E9="",F9=""),"",IF(D9="Long",(F9-E9)*G9,(E9-F9)*G9)) | K9: =IF(I9="","",I9-J9) | L9: =IF(K9="","",K9/H9*100) | M9: =IF(K9="","",IF(K9>0,"WIN",IF(K9<0,"LOSS","EVEN")))
H10: =IF(E10="","",E10*G10) | I10: =IF(OR(E10="",F10=""),"",IF(D10="Long",(F10-E10)*G10,(E10-F10)*G10)) | K10: =IF(I10="","",I10-J10) | L10: =IF(K10="","",K10/H10*100) | M10: =IF(K10="","",IF(K10>0,"WIN",IF(K10<0,"LOSS","EVEN")))
H11: =IF(E11="","",E11*G11) | I11: =IF(OR(E11="",F11=""),"",IF(D11="Long",(F11-E11)*G11,(E11-F11)*G11)) | K11: =IF(I11="","",I11-J11) | L11: =IF(K11="","",K11/H11*100) | M11: =IF(K11="","",IF(K11>0,"WIN",IF(K11<0,"LOSS","EVEN")))
H12: =IF(E12="","",E12*G12) | I12: =IF(OR(E12="",F12=""),"",IF(D12="Long",(F12-E12)*G12,(E12-F12)*G12)) | K12: =IF(I12="","",I12-J12) | L12: =IF(K12="","",K12/H12*100) | M12: =IF(K12="","",IF(K12>0,"WIN",IF(K12<0,"LOSS","EVEN")))
H13: =IF(E13="","",E13*G13) | I13: =IF(OR(E13="",F13=""),"",IF(D13="Long",(F13-E13)*G13,(E13-F13)*G13)) | K13: =IF(I13="","",I13-J13) | L13: =IF(K13="","",K13/H13*100) | M13: =IF(K13="","",IF(K13>0,"WIN",IF(K13<0,"LOSS","EVEN")))
H14: =IF(E14="","",E14*G14) | I14: =IF(OR(E14="",F14=""),"",IF(D14="Long",(F14-E14)*G14,(E14-F14)*G14)) | K14: =IF(I14="","",I14-J14) | L14: =IF(K14="","",K14/H14*100) | M14: =IF(K14="","",IF(K14>0,"WIN",IF(K14<0,"LOSS","EVEN")))
H15: =IF(E15="","",E15*G15) | I15: =IF(OR(E15="",F15=""),"",IF(D15="Long",(F15-E15)*G15,(E15-F15)*G15)) | K15: =IF(I15="","",I15-J15) | L15: =IF(K15="","",K15/H15*100) | M15: =IF(K15="","",IF(K15>0,"WIN",IF(K15<0,"LOSS","EVEN")))
H16: =IF(E16="","",E16*G16) | I16: =IF(OR(E16="",F16=""),"",IF(D16="Long",(F16-E16)*G16,(E16-F16)*G16)) | K16: =IF(I16="","",I16-J16) | L16: =IF(K16="","",K16/H16*100) | M16: =IF(K16="","",IF(K16>0,"WIN",IF(K16<0,"LOSS","EVEN")))
H17: =IF(E17="","",E17*G17) | I17: =IF(OR(E17="",F17=""),"",IF(D17="Long",(F17-E17)*G17,(E17-F17)*G17)) | K17: =IF(I17="","",I17-J17) | L17: =IF(K17="","",K17/H17*100) | M17: =IF(K17="","",IF(K17>0,"WIN",IF(K17<0,"LOSS","EVEN")))
... H55: =IF(E55="","",E55*G55) | I55: =IF(OR(E55="",F55=""),"",IF(D55="Long",(F55-E55)*G55,(E55-F55)*G55)) | K55: =IF(I55="","",I55-J55) | L55: =IF(K55="","",K55/H55*100) | M55: =IF(K55="","",IF(K55>0,"WIN",IF(K55<0,"LOSS","EVEN")))

Sheet Performance
A1: TRADING PERFORMANCE METRICS
A3: OVERALL PERFORMANCE
A5: Total Trades | B5: =COUNTA('Trade Journal'!A6:A55) -> 0
A6: Winning Trades | B6: =COUNTIF('Trade Journal'!M6:M55,"WIN") -> 0
A7: Losing Trades | B7: =COUNTIF('Trade Journal'!M6:M55,"LOSS") -> 0
A8: Win Rate | B8: =IF(B5>0,B6/B5,0) -> 0
A9: Total Net P&L | B9: =SUM('Trade Journal'!K6:K55) -> 0
A10: Average Win | B10: =IF(B6>0,SUMIF('Trade Journal'!M6:M55,"WIN",'Trade Journal'!K6:K55)/B6,0) -> 0
A11: Average Loss | B11: =IF(B7>0,SUMIF('Trade Journal'!M6:M55,"LOSS",'Trade Journal'!K6:K55)/B7,0) -> 0
A12: Profit Factor | B12: =IF(B11<>0,-SUMIF('Trade Journal'!M6:M55,"WIN",'Trade Journal'!K6:K55)/SUMIF('Trade Journal'!M6:M55,"LOSS",'Trade Journal'!K6:K55),0) -> 0
A13: Expectancy | B13: =IF(B5>0,B9/B5,0) -> 0
A14: Largest Win | B14: =MAX('Trade Journal'!K6:K55) -> 0
A15: Largest Loss | B15: =MIN('Trade Journal'!K6:K55) -> 0
A16: Max Consecutive Wins
A17: Max Consecutive Losses
A19: TARGETS & THRESHOLDS
A20: Target Win Rate | B20: 0.4
A21: Max Drawdown Threshold | B21: 0.05
A22: Max Daily Loss | B22: 0.02
A23: Max Position Size | B23: 0.2

Sheet Equity Curve
A1: EQUITY CURVE TRACKER
A2: Track your account balance over time
A4: Date | B4: Starting Balance | C4: Deposits/Withdrawals | D4: Net P&L | E4: Ending Balance | F4: High Water Mark | G4: Drawdown | H4: Drawdown %
A5: 2026-01-31 | B5: 10000 | C5: 0 | D5: 0 | E5: =B5+C5+D5 -> 10000 | F5: =E5 -> 10000 | G5: =F5-E5 -> 0 | H5: =IF(F5>0,G5/F5,0) -> 0
B6: =E5 -> 10000 | E6: =IF(B6="","",B6+C6+D6) -> 10000 | F6: =IF(E6="","",MAX(F5,E6)) -> 10000 | G6: =IF(E6="","",F6-E6) -> 0 | H6: =IF(F6>0,G6/F6,0) -> 0
B7: =E6 -> 10000 | E7: =IF(B7="","",B7+C7+D7) -> 10000 | F7: =IF(E7="","",MAX(F6,E7)) -> 10000 | G7: =IF(E7="","",F7-E7) -> 0 | H7: =IF(F7>0,G7/F7,0) -> 0
B8: =E7 -> 10000 | E8: =IF(B8="","",B8+C8+D8) -> 10000 | F8: =IF(E8="","",MAX(F7,E8)) -> 10000 | G8: =IF(E8="","",F8-E8) -> 0 | H8: =IF(F8>0,G8/F8,0) -> 0
B9: =E8 -> 10000 | E9: =IF(B9="","",B9+C9+D9) -> 10000 | F9: =IF(E9="","",MAX(F8,E9)) -> 10000 | G9: =IF(E9="","",F9-E9) -> 0 | H9: =IF(F9>0,G9/F9,0) -> 0
B10: =E9 -> 10000 | E10: =IF(B10="","",B10+C10+D10) -> 10000 | F10: =IF(E10="","",MAX(F9,E10)) -> 10000 | G10: =IF(E10="","",F10-E10) -> 0 | H10: =IF(F10>0,G10/F10,0) -> 0
B11: =E10 -> 10000 | E11: =IF(B11="","",B11+C11+D11) -> 10000 | F11: =IF(E11="","",MAX(F10,E11)) -> 10000 | G11: =IF(E11="","",F11-E11) -> 0 | H11: =IF(F11>0,G11/F11,0) -> 0
B12: =E11 -> 10000 | E12: =IF(B12="","",B12+C12+D12) -> 10000 | F12: =IF(E12="","",MAX(F11,E12)) -> 10000 | G12: =IF(E12="","",F12-E12) -> 0 | H12: =IF(F12>0,G12/F12,0) -> 0
B13: =E12 -> 10000 | E13: =IF(B13="","",B13+C13+D13) -> 10000 | F13: =IF(E13="","",MAX(F12,E13)) -> 10000 | G13: =IF(E13="","",F13-E13) -> 0 | H13: =IF(F13>0,G13/F13,0) -> 0
B14: =E13 -> 10000 | E14: =IF(B14="","",B14+C14+D14) -> 10000 | F14: =IF(E14="","",MAX(F13,E14)) -> 10000 | G14: =IF(E14="","",F14-E14) -> 0 | H14: =IF(F14>0,G14/F14,0) -> 0
B15: =E14 -> 10000 | E15: =IF(B15="","",B15+C15+D15) -> 10000 | F15: =IF(E15="","",MAX(F14,E15)) -> 10000 | G15: =IF(E15="","",F15-E15) -> 0 | H15: =IF(F15>0,G15/F15,0) -> 0
B16: =E15 -> 10000 | E16: =IF(B16="","",B16+C16+D16) -> 10000 | F16: =IF(E16="","",MAX(F15,E16)) -> 10000 | G16: =IF(E16="","",F16-E16) -> 0 | H16: =IF(F16>0,G16/F16,0) -> 0
B17: =E16 -> 10000 | E17: =IF(B17="","",B17+C17+D17) -> 10000 | F17: =IF(E17="","",MAX(F16,E17)) -> 10000 | G17: =IF(E17="","",F17-E17) -> 0 | H17: =IF(F17>0,G17/F17,0) -> 0
... B55: =E54 -> 10000 | E55: =IF(B55="","",B55+C55+D55) -> 10000 | F55: =IF(E55="","",MAX(F54,E55)) -> 10000 | G55: =IF(E55="","",F55-E55) -> 0 | H55: =IF(F55>0,G55/F55,0) -> 0

Sheet Strategy Lab
A1: STRATEGY LAB
A2: Document hypotheses, test them, record results
A4: ID | B4: Hypothesis | C4: Rules | D4: Start Date | E4: End Date | F4: Trades | G4: Win Rate | H4: Net P&L | I4: Status | J4: Conclusion
A5: 1 | B5: (Example) Mean reversion works on high-volume stocks | C5: Entry: RSI < 30, Exit: RSI > 50, Stop: -2% | I5: Testing

Sheet Lessons Log
A1: LESSONS LEARNED
A2: Patterns, mistakes, insights - review monthly
A4: Date | B4: Category | C4: Lesson | D4: Action Taken | E4: Recurring? | G4: Categories:
G5: Entry
G6: Exit
G7: Position Size
G8: Risk Mgmt
G9: Psychology
G10: Market Read
G11: Process
