Workbook

Sheet Item SKUs
A1: Item ID | B1: Name | C1: Business Unit | D1: Category | E1: Sub-Category | F1: SKU | G1: Brand | H1: Cost Price ( MYR ) | I1: Stock Moving Status | J1: List Price
B2: KINETICO MACH 4060s OD (Activated Carbon/Softening Resin) | C2: Water: Residential (B2C) | D2: 6. Water Treatment | E2: Softening Systems | F2: 11215 | G2: KINETICO | J2: =CEILING((Query1[[#This Row],[Cost Price ( MYR )]] / (1 - _xlfn.XLOOKUP(Query1[[#This Row],[Business Unit]], Margins!A:A, Margins!C:C))) * (1 - _xlfn.XLOOKUP(Query1[[#This Row],[Business Unit]], Margins!A:A, Margins!D:D)),5) -> 0
B3: KINETICO AIR TANK - QUICKFLO STORAGE TANK, 3 GALLON, BLACK | C3: Water: Residential (B2C) | D3: 6. Water Treatment | E3: Filtration Systems | F3: 12754 | G3: KINETICO | J3: =CEILING((Query1[[#This Row],[Cost Price ( MYR )]] / (1 - _xlfn.XLOOKUP(Query1[[#This Row],[Business Unit]], Margins!A:A, Margins!C:C))) * (1 - _xlfn.XLOOKUP(Query1[[#This Row],[Business Unit]], Margins!A:A, Margins!D:D)),5) -> 0
A4: 4602503000000445755 | B4: KINETICO Drinking Water Filter with MacguardÃ¢â€žÂ¢ - Model 7500 (Lead/ VOC/Cyst) | C4: Water: Residential (B2C) | D4: 6. Water Treatment | E4: Filtration Systems | F4: 4050A | G4: KINETICO | H4: 0 | J4: =CEILING((Query1[[#This Row],[Cost Price ( MYR )]] / (1 - _xlfn.XLOOKUP(Query1[[#This Row],[Business Unit]], Margins!A:A, Margins!C:C))) * (1 - _xlfn.XLOOKUP(Query1[[#This Row],[Business Unit]], Margins!A:A, Margins!D:D)),5) -> 0
A5: 4602503000000158057 | B5: KINETICO FC-550 DRINKING WATER STATION | C5: Water: Residential (B2C) | D5: 6. Water Treatment | E5: Filtration Systems | F5: 100-1000 | G5: KINETICO | H5: 0 | J5: =CEILING((Query1[[#This Row],[Cost Price ( MYR )]] / (1 - _xlfn.XLOOKUP(Query1[[#This Row],[Business Unit]], Margins!A:A, Margins!C:C))) * (1 - _xlfn.XLOOKUP(Query1[[#This Row],[Business Unit]], Margins!A:A, Margins!D:D)),5) -> 0
A6: 4602503000000446987 | B6: KINETICO Faucet, Economy Chrome Drinking | C6: Water: Residential (B2C) | D6: 6. Water Treatment | E6: Filtration Systems | F6: S11450B | G6: KINETICO | H6: 118.33 | J6: =CEILING((Query1[[#This Row],[Cost Price ( MYR )]] / (1 - _xlfn.XLOOKUP(Query1[[#This Row],[Business Unit]], Margins!A:A, Margins!C:C))) * (1 - _xlfn.XLOOKUP(Query1[[#This Row],[Business Unit]], Margins!A:A, Margins!D:D)),5) -> 215
B7: KINETICO K5 Core | C7: Water: Residential (B2C) | D7: 6. Water Treatment | E7: Filtration Systems | F7: 12799 | G7: KINETICO | J7: =CEILING((Query1[[#This Row],[Cost Price ( MYR )]] / (1 - _xlfn.XLOOKUP(Query1[[#This Row],[Business Unit]], Margins!A:A, Margins!C:C))) * (1 - _xlfn.XLOOKUP(Query1[[#This Row],[Business Unit]], Margins!A:A, Margins!D:D)),5) -> 0
B8: KINETICO MACH 2060f OD with Activated Carbon | C8: Water: Residential (B2C) | D8: 6. Water Treatment | E8: Filtration Systems | F8: 11207 | G8: KINETICO | J8: =CEILING((Query1[[#This Row],[Cost Price ( MYR )]] / (1 - _xlfn.XLOOKUP(Query1[[#This Row],[Business Unit]], Margins!A:A, Margins!C:C))) * (1 - _xlfn.XLOOKUP(Query1[[#This Row],[Business Unit]], Margins!A:A, Margins!D:D)),5) -> 0
B9: KINETICO MACH 2060s OD 18 x 35 Brine Drum | C9: Water: Residential (B2C) | D9: 6. Water Treatment | E9: Softening Systems | F9: 11201 | G9: KINETICO | J9: =CEILING((Query1[[#This Row],[Cost Price ( MYR )]] / (1 - _xlfn.XLOOKUP(Query1[[#This Row],[Business Unit]], Margins!A:A, Margins!C:C))) * (1 - _xlfn.XLOOKUP(Query1[[#This Row],[Business Unit]], Margins!A:A, Margins!D:D)),5) -> 0
A10: 4602503000000097500 | B10: KINETICO MACH CP213f OD with Activated Carbon | C10: Water: Residential (B2C) | D10: 6. Water Treatment | E10: Filtration Systems | F10: 11244A | G10: KINETICO | H10: 5830.09 | J10: =CEILING((Query1[[#This Row],[Cost Price ( MYR )]] / (1 - _xlfn.XLOOKUP(Query1[[#This Row],[Business Unit]], Margins!A:A, Margins!C:C))) * (1 - _xlfn.XLOOKUP(Query1[[#This Row],[Business Unit]], Margins!A:A, Margins!D:D)),5) -> 10370
B11: KINETICO MACH CP213f OD with Macrolite | C11: Water: Residential (B2C) | D11: 6. Water Treatment | E11: Filtration Systems | F11: 11246 | G11: KINETICO | J11: =CEILING((Query1[[#This Row],[Cost Price ( MYR )]] / (1 - _xlfn.XLOOKUP(Query1[[#This Row],[Business Unit]], Margins!A:A, Margins!C:C))) * (1 - _xlfn.XLOOKUP(Query1[[#This Row],[Business Unit]], Margins!A:A, Margins!D:D)),5) -> 0
A12: 4602503000000445513 | B12: KINETICO MACH CP213s OD 24 x 40 Brine Drum | C12: Water: Residential (B2C) | D12: 6. Water Treatment | E12: Softening Systems | F12: 11180A | G12: KINETICO | H12: 6684.97 | J12: =CEILING((Query1[[#This Row],[Cost Price ( MYR )]] / (1 - _xlfn.XLOOKUP(Query1[[#This Row],[Business Unit]], Margins!A:A, Margins!C:C))) * (1 - _xlfn.XLOOKUP(Query1[[#This Row],[Business Unit]], Margins!A:A, Margins!D:D)),5) -> 11895
A13: 4602503000021500020 | B13: KINETICO MACH CP216s OD 24 x 40 Brine Drum | C13: Water: Residential (B2C) | D13: 6. Water Treatment | E13: Softening Systems | F13: 11182A | G13: KINETICO | H13: 14067.25 | J13: =CEILING((Query1[[#This Row],[Cost Price ( MYR )]] / (1 - _xlfn.XLOOKUP(Query1[[#This Row],[Business Unit]], Margins!A:A, Margins!C:C))) * (1 - _xlfn.XLOOKUP(Query1[[#This Row],[Business Unit]], Margins!A:A, Margins!D:D)),5) -> 25025
B14: KINETICO MACH Prefilter 10Ã¢â‚¬Â NORYL (Indoor) 5Micron | C14: Water: Residential (B2C) | D14: 6. Water Treatment | E14: Filtration Systems | F14: 11825 | G14: KINETICO | J14: =CEILING((Query1[[#This Row],[Cost Price ( MYR )]] / (1 - _xlfn.XLOOKUP(Query1[[#This Row],[Business Unit]], Margins!A:A, Margins!C:C))) * (1 - _xlfn.XLOOKUP(Query1[[#This Row],[Business Unit]], Margins!A:A, Margins!D:D)),5) -> 0
B15: KINETICO MACH Prefilter 16Ã¢â‚¬Â NORYL (Indoor) 5Micron | C15: Water: Residential (B2C) | D15: 6. Water Treatment | E15: Filtration Systems | F15: 11826 | G15: KINETICO | J15: =CEILING((Query1[[#This Row],[Cost Price ( MYR )]] / (1 - _xlfn.XLOOKUP(Query1[[#This Row],[Business Unit]], Margins!A:A, Margins!C:C))) * (1 - _xlfn.XLOOKUP(Query1[[#This Row],[Business Unit]], Margins!A:A, Margins!D:D)),5) -> 0
B16: KINETICO POU - PREMIER COMPACT WATER SOFTENER | C16: Water: Residential (B2C) | D16: 6. Water Treatment | E16: Softening Systems | F16: 16145 | G16: KINETICO | J16: =CEILING((Query1[[#This Row],[Cost Price ( MYR )]] / (1 - _xlfn.XLOOKUP(Query1[[#This Row],[Business Unit]], Margins!A:A, Margins!C:C))) * (1 - _xlfn.XLOOKUP(Query1[[#This Row],[Business Unit]], Margins!A:A, Margins!D:D)),5) -> 0
A17: 4602503000000446481 | B17: KINETICO POU - PREMIER UF FILTER | C17: Water: Residential (B2C) | D17: 6. Water Treatment | E17: Filtration Systems | F17: 100-500-INT | G17: KINETICO | H17: 0 | J17: =CEILING((Query1[[#This Row],[Cost Price ( MYR )]] / (1 - _xlfn.XLOOKUP(Query1[[#This Row],[Business Unit]], Margins!A:A, Margins!C:C))) * (1 - _xlfn.XLOOKUP(Query1[[#This Row],[Business Unit]], Margins!A:A, Margins!D:D)),5) -> 0
B18: KINETICO PREMIER SERIES MACH 4060F OD, MACROLITE/ACTIVATED CARBON | C18: Water: Residential (B2C) | D18: 6. Water Treatment | E18: Filtration Systems | F18: 11232 | G18: KINETICO | J18: =CEILING((Query1[[#This Row],[Cost Price ( MYR )]] / (1 - _xlfn.XLOOKUP(Query1[[#This Row],[Business Unit]], Margins!A:A, Margins!C:C))) * (1 - _xlfn.XLOOKUP(Query1[[#This Row],[Business Unit]], Margins!A:A, Margins!D:D)),5) -> 0
B19: KINETICO PREMIER SERIES MACH 4060S OD, MACROLITE | C19: Water: Residential (B2C) | D19: 6. Water Treatment | E19: Softening Systems | F19: 11223 | G19: KINETICO | J19: =CEILING((Query1[[#This Row],[Cost Price ( MYR )]] / (1 - _xlfn.XLOOKUP(Query1[[#This Row],[Business Unit]], Margins!A:A, Margins!C:C))) * (1 - _xlfn.XLOOKUP(Query1[[#This Row],[Business Unit]], Margins!A:A, Margins!D:D)),5) -> 0
A20: 4602503000000097192 | B20: KINETICO PREMIER SERIESÃ‚Â® MACH 2100F OD, MACROLITEÃ‚Â® | C20: Water: Residential (B2C) | D20: 6. Water Treatment | E20: Filtration Systems | F20: 11146A | G20: KINETICO | H20: 4375.67 | J20: =CEILING((Query1[[#This Row],[Cost Price ( MYR )]] / (1 - _xlfn.XLOOKUP(Query1[[#This Row],[Business Unit]], Margins!A:A, Margins!C:C))) * (1 - _xlfn.XLOOKUP(Query1[[#This Row],[Business Unit]], Margins!A:A, Margins!D:D)),5) -> 7785
B21: Kinetico Faucet Classic Chrome | C21: Water: Residential (B2C) | D21: 6. Water Treatment | E21: Filtration Systems | F21: 12725 | G21: KINETICO | J21: =CEILING((Query1[[#This Row],[Cost Price ( MYR )]] / (1 - _xlfn.XLOOKUP(Query1[[#This Row],[Business Unit]], Margins!A:A, Margins!C:C))) * (1 - _xlfn.XLOOKUP(Query1[[#This Row],[Business Unit]], Margins!A:A, Margins!D:D)),5) -> 0
B22: Kinetico Premier Series MACh 2030F OD, MACrolite | C22: Water: Residential (B2C) | D22: 6. Water Treatment | E22: Filtration Systems | F22: 12662 | G22: KINETICO | J22: =CEILING((Query1[[#This Row],[Cost Price ( MYR )]] / (1 - _xlfn.XLOOKUP(Query1[[#This Row],[Business Unit]], Margins!A:A, Margins!C:C))) * (1 - _xlfn.XLOOKUP(Query1[[#This Row],[Business Unit]], Margins!A:A, Margins!D:D)),5) -> 0
B23: Kinetico Premier Series MACh 2060F OD, MACrolite | C23: Water: Residential (B2C) | D23: 6. Water Treatment | E23: Filtration Systems | F23: 11211 | G23: KINETICO | J23: =CEILING((Query1[[#This Row],[Cost Price ( MYR )]] / (1 - _xlfn.XLOOKUP(Query1[[#This Row],[Business Unit]], Margins!A:A, Margins!C:C))) * (1 - _xlfn.XLOOKUP(Query1[[#This Row],[Business Unit]], Margins!A:A, Margins!D:D)),5) -> 0
A24: 4602503000000445898 | B24: Kinetico Storage Tank Air Charge 3 Gallons | C24: Water: Residential (B2C) | D24: 6. Water Treatment | E24: Filtration Systems | F24: 9344B | G24: KINETICO | H24: 0 | J24: =CEILING((Query1[[#This Row],[Cost Price ( MYR )]] / (1 - _xlfn.XLOOKUP(Query1[[#This Row],[Business Unit]], Margins!A:A, Margins!C:C))) * (1 - _xlfn.XLOOKUP(Query1[[#This Row],[Business Unit]], Margins!A:A, Margins!D:D)),5) -> 0
B25: TANK, STORAGE TANK ASSEMBLY - 14 GALLON, A200 | C25: Water: Residential (B2C) | D25: 6. Water Treatment | E25: Filtration Systems | F25: 104170 | G25: KINETICO | J25: =CEILING((Query1[[#This Row],[Cost Price ( MYR )]] / (1 - _xlfn.XLOOKUP(Query1[[#This Row],[Business Unit]], Margins!A:A, Margins!C:C))) * (1 - _xlfn.XLOOKUP(Query1[[#This Row],[Business Unit]], Margins!A:A, Margins!D:D)),5) -> 0
A26: 4602503000021500139 | B26: AVENTURA - TOP BOTTOM HUB & LATERAL | C26: Water: Residential (B2C) | D26: 6. Water Treatment | E26: Filtration Systems | F26: AV-421-63 | G26: AVENTURA | H26: 0 | J26: =CEILING((Query1[[#This Row],[Cost Price ( MYR )]] / (1 - _xlfn.XLOOKUP(Query1[[#This Row],[Business Unit]], Margins!A:A, Margins!C:C))) * (1 - _xlfn.XLOOKUP(Query1[[#This Row],[Business Unit]], Margins!A:A, Margins!D:D)),5) -> 0
A27: 4602503000021500156 | B27: AVENTURA - TOP BOTTOM HUB & LATERAL | C27: Water: Residential (B2C) | D27: 6. Water Treatment | E27: Filtration Systems | F27: AV-436-63 | G27: AVENTURA | H27: 0 | J27: =CEILING((Query1[[#This Row],[Cost Price ( MYR )]] / (1 - _xlfn.XLOOKUP(Query1[[#This Row],[Business Unit]], Margins!A:A, Margins!C:C))) * (1 - _xlfn.XLOOKUP(Query1[[#This Row],[Business Unit]], Margins!A:A, Margins!D:D)),5) -> 0
A28: 4602503000021500122 | B28: AVENTURA - TOP BOTTOM HUB & LATERAL - FOR POE FILTER - 4272 | C28: Water: Residential (B2C) | D28: 6. Water Treatment | E28: Filtration Systems | F28: AV6F42-75L | G28: AVENTURA | H28: 0 | J28: =CEILING((Query1[[#This Row],[Cost Price ( MYR )]] / (1 - _xlfn.XLOOKUP(Query1[[#This Row],[Business Unit]], Margins!A:A, Margins!C:C))) * (1 - _xlfn.XLOOKUP(Query1[[#This Row],[Business Unit]], Margins!A:A, Margins!D:D)),5) -> 0
A29: 4602503000021500088 | B29: AVENTURA - TOP STACK DIFFUSER -FOR POE FILTER - 2162 & 3072 & 3672 | C29: Water: Residential (B2C) | D29: 6. Water Treatment | E29: Filtration Systems | F29: AV-4R2-63 | G29: AVENTURA | H29: 0 | J29: =CEILING((Query1[[#This Row],[Cost Price ( MYR )]] / (1 - _xlfn.XLOOKUP(Query1[[#This Row],[Business Unit]], Margins!A:A, Margins!C:C))) * (1 - _xlfn.XLOOKUP(Query1[[#This Row],[Business Unit]], Margins!A:A, Margins!D:D)),5) -> 0
A30: 4602503000021500105 | B30: AVENTURA - TOP TOP HUB & LATERAL -FOR POE FILTER - 4272 | C30: Water: Residential (B2C) | D30: 6. Water Treatment | E30: Filtration Systems | F30: AV-6F42-75U | G30: AVENTURA | H30: 0 | J30: =CEILING((Query1[[#This Row],[Cost Price ( MYR )]] / (1 - _xlfn.XLOOKUP(Query1[[#This Row],[Business Unit]], Margins!A:A, Margins!C:C))) * (1 - _xlfn.XLOOKUP(Query1[[#This Row],[Business Unit]], Margins!A:A, Margins!D:D)),5) -> 0
A31: 4602503000000622357 | B31: AVENTURA BYPASS VALVE - M88 | C31: Water: Residential (B2C) | D31: 6. Water Treatment | E31: Filtration Systems | F31: T-0345 | G31: AVENTURA | H31: 0 | J31: =CEILING((Query1[[#This Row],[Cost Price ( MYR )]] / (1 - _xlfn.XLOOKUP(Query1[[#This Row],[Business Unit]], Margins!A:A, Margins!C:C))) * (1 - _xlfn.XLOOKUP(Query1[[#This Row],[Business Unit]], Margins!A:A, Margins!D:D)),5) -> 0
A32: 4602503000000615565 | B32: AVENTURA POE FILTER - 1044 | C32: Water: Residential (B2C) | D32: 6. Water Treatment | E32: Filtration Systems | F32: T-0247 | G32: AVENTURA | H32: 0 | J32: =CEILING((Query1[[#This Row],[Cost Price ( MYR )]] / (1 - _xlfn.XLOOKUP(Query1[[#This Row],[Business Unit]], Margins!A:A, Margins!C:C))) * (1 - _xlfn.XLOOKUP(Query1[[#This Row],[Business Unit]], Margins!A:A, Margins!D:D)),5) -> 0
A33: 4602503000000615584 | B33: AVENTURA POE FILTER - 1054 | C33: Water: Residential (B2C) | D33: 6. Water Treatment | E33: Filtration Systems | F33: T-0249 | G33: AVENTURA | H33: 0 | J33: =CEILING((Query1[[#This Row],[Cost Price ( MYR )]] / (1 - _xlfn.XLOOKUP(Query1[[#This Row],[Business Unit]], Margins!A:A, Margins!C:C))) * (1 - _xlfn.XLOOKUP(Query1[[#This Row],[Business Unit]], Margins!A:A, Margins!D:D)),5) -> 0
A34: 4602503000021500037 | B34: AVENTURA POE FILTER - 2162 | C34: Water: Residential (B2C) | D34: 6. Water Treatment | E34: Filtration Systems | F34: T-02162 | G34: AVENTURA | H34: 0 | J34: =CEILING((Query1[[#This Row],[Cost Price ( MYR )]] / (1 - _xlfn.XLOOKUP(Query1[[#This Row],[Business Unit]], Margins!A:A, Margins!C:C))) * (1 - _xlfn.XLOOKUP(Query1[[#This Row],[Business Unit]], Margins!A:A, Margins!D:D)),5) -> 0
A35: 4602503000021500054 | B35: AVENTURA POE FILTER - 2672 | C35: Water: Residential (B2C) | D35: 6. Water Treatment | E35: Filtration Systems | F35: T-02672 | G35: AVENTURA | H35: 0 | J35: =CEILING((Query1[[#This Row],[Cost Price ( MYR )]] / (1 - _xlfn.XLOOKUP(Query1[[#This Row],[Business Unit]], Margins!A:A, Margins!C:C))) * (1 - _xlfn.XLOOKUP(Query1[[#This Row],[Business Unit]], Margins!A:A, Margins!D:D)),5) -> 0
A36: 4602503000000622571 | B36: AVENTURA POE FILTER - 3072 | C36: Water: Residential (B2C) | D36: 6. Water Treatment | E36: Filtration Systems | F36: T-0348 | G36: AVENTURA | H36: 0 | J36: =CEILING((Query1[[#This Row],[Cost Price ( MYR )]] / (1 - _xlfn.XLOOKUP(Query1[[#This Row],[Business Unit]], Margins!A:A, Margins!C:C))) * (1 - _xlfn.XLOOKUP(Query1[[#This Row],[Business Unit]], Margins!A:A, Margins!D:D)),5) -> 0
A37: 4602503000021500071 | B37: AVENTURA POE FILTER - 4272 | C37: Water: Residential (B2C) | D37: 6. Water Treatment | E37: Filtration Systems | F37: T-04272 | G37: AVENTURA | H37: 0 | J37: =CEILING((Query1[[#This Row],[Cost Price ( MYR )]] / (1 - _xlfn.XLOOKUP(Query1[[#This Row],[Business Unit]], Margins!A:A, Margins!C:C))) * (1 - _xlfn.XLOOKUP(Query1[[#This Row],[Business Unit]], Margins!A:A, Margins!D:D)),5) -> 0
... A39: 4602503000000615554 | B39: AVENTURA POE FILTER - 844 | C39: Water: Residential (B2C) | D39: 6. Water Treatment | E39: Filtration Systems | F39: T-0245 | G39: AVENTURA | H39: 0 | J39: =CEILING((Query1[[#This Row],[Cost Price ( MYR )]] / (1 - _xlfn.XLOOKUP(Query1[[#This Row],[Business Unit]], Margins!A:A, Margins!C:C))) * (1 - _xlfn.XLOOKUP(Query1[[#This Row],[Business Unit]], Margins!A:A, Margins!D:D)),5) -> 0
A40: 4602503000000449486 | B40: KINETICO BYPASS VALVE | C40: Water: Residential (B2C) | D40: 6. Water Treatment | E40: Filtration Systems | F40: T-0271 | H40: 0 | J40: =CEILING((Query1[[#This Row],[Cost Price ( MYR )]] / (1 - _xlfn.XLOOKUP(Query1[[#This Row],[Business Unit]], Margins!A:A, Margins!C:C))) * (1 - _xlfn.XLOOKUP(Query1[[#This Row],[Business Unit]], Margins!A:A, Margins!D:D)),5) -> 0
B41: KINETICO DISTRIBUTOR TUBES - 7X35 UI KI, 2030 | C41: Water: Residential (B2C) | D41: 6. Water Treatment | E41: Treatment Spares | F41: 16810 | G41: KINETICO | J41: =CEILING((Query1[[#This Row],[Cost Price ( MYR )]] / (1 - _xlfn.XLOOKUP(Query1[[#This Row],[Business Unit]], Margins!A:A, Margins!C:C))) * (1 - _xlfn.XLOOKUP(Query1[[#This Row],[Business Unit]], Margins!A:A, Margins!D:D)),5) -> 0
B42: KINETICO DISTRIBUTOR TUBES - 8X40 UI KI, 2060 | C42: Water: Residential (B2C) | D42: 6. Water Treatment | E42: Treatment Spares | F42: 13439 | G42: KINETICO | J42: =CEILING((Query1[[#This Row],[Cost Price ( MYR )]] / (1 - _xlfn.XLOOKUP(Query1[[#This Row],[Business Unit]], Margins!A:A, Margins!C:C))) * (1 - _xlfn.XLOOKUP(Query1[[#This Row],[Business Unit]], Margins!A:A, Margins!D:D)),5) -> 0
A43: 4602503000021500241 | B43: KINETICO FAUCET - FOR PUREFECTA | C43: Water: Residential (B2C) | D43: 6. Water Treatment | E43: Treatment Spares | F43: 10809P | G43: KINETICO | H43: 0 | J43: =CEILING((Query1[[#This Row],[Cost Price ( MYR )]] / (1 - _xlfn.XLOOKUP(Query1[[#This Row],[Business Unit]], Margins!A:A, Margins!C:C))) * (1 - _xlfn.XLOOKUP(Query1[[#This Row],[Business Unit]], Margins!A:A, Margins!D:D)),5) -> 0
B44: KINETICO K5 Core | C44: Water: Residential (B2C) | D44: 6. Water Treatment | E44: Treatment Spares | F44: 12799 | G44: KINETICO | J44: =CEILING((Query1[[#This Row],[Cost Price ( MYR )]] / (1 - _xlfn.XLOOKUP(Query1[[#This Row],[Business Unit]], Margins!A:A, Margins!C:C))) * (1 - _xlfn.XLOOKUP(Query1[[#This Row],[Business Unit]], Margins!A:A, Margins!D:D)),5) -> 0
A45: 4602503000021500190 | B45: KINETICO MACH 2030s OD 18 x 35 Brine Drum | C45: Water: Residential (B2C) | D45: 6. Water Treatment | E45: Softening Systems | F45: 11020A | G45: KINETICO | H45: 0 | J45: =CEILING((Query1[[#This Row],[Cost Price ( MYR )]] / (1 - _xlfn.XLOOKUP(Query1[[#This Row],[Business Unit]], Margins!A:A, Margins!C:C))) * (1 - _xlfn.XLOOKUP(Query1[[#This Row],[Business Unit]], Margins!A:A, Margins!D:D)),5) -> 0
B46: KINETICO PUREFECTA - DRINKING WATER SYSTEM | C46: Water: Residential (B2C) | D46: 6. Water Treatment | E46: Filtration Systems | F46: 10644 | G46: KINETICO | J46: =CEILING((Query1[[#This Row],[Cost Price ( MYR )]] / (1 - _xlfn.XLOOKUP(Query1[[#This Row],[Business Unit]], Margins!A:A, Margins!C:C))) * (1 - _xlfn.XLOOKUP(Query1[[#This Row],[Business Unit]], Margins!A:A, Margins!D:D)),5) -> 0
B47: KINETICO SILICONE PACKET | C47: Water: Residential (B2C) | D47: 6. Water Treatment | E47: Treatment Spares | F47: 1452 | G47: KINETICO | J47: =CEILING((Query1[[#This Row],[Cost Price ( MYR )]] / (1 - _xlfn.XLOOKUP(Query1[[#This Row],[Business Unit]], Margins!A:A, Margins!C:C))) * (1 - _xlfn.XLOOKUP(Query1[[#This Row],[Business Unit]], Margins!A:A, Margins!D:D)),5) -> 0
A48: 4602503000000447273 | B48: KINETICO VALVE PARTS - FILTER HEAD CAP, DFFR B/W-ULTEM-WHITE | C48: Water: Residential (B2C) | D48: 6. Water Treatment | E48: Treatment Spares | F48: 8697B | G48: KINETICO | H48: 18.96 | J48: =CEILING((Query1[[#This Row],[Cost Price ( MYR )]] / (1 - _xlfn.XLOOKUP(Query1[[#This Row],[Business Unit]], Margins!A:A, Margins!C:C))) * (1 - _xlfn.XLOOKUP(Query1[[#This Row],[Business Unit]], Margins!A:A, Margins!D:D)),5) -> 35
B49: KINETICO VALVE PARTS - IN/OUT ADAPTER, MALE E CLIP, 1.25", GFN PLASTIC | C49: Water: Residential (B2C) | D49: 6. Water Treatment | E49: Treatment Spares | F49: 10739 | G49: KINETICO | J49: =CEILING((Query1[[#This Row],[Cost Price ( MYR )]] / (1 - _xlfn.XLOOKUP(Query1[[#This Row],[Business Unit]], Margins!A:A, Margins!C:C))) * (1 - _xlfn.XLOOKUP(Query1[[#This Row],[Business Unit]], Margins!A:A, Margins!D:D)),5) -> 0
B50: KINETICO VALVE PARTS - METER DISC #1 | C50: Water: Residential (B2C) | D50: 6. Water Treatment | E50: Treatment Spares | F50: 1504 | G50: KINETICO | J50: =CEILING((Query1[[#This Row],[Cost Price ( MYR )]] / (1 - _xlfn.XLOOKUP(Query1[[#This Row],[Business Unit]], Margins!A:A, Margins!C:C))) * (1 - _xlfn.XLOOKUP(Query1[[#This Row],[Business Unit]], Margins!A:A, Margins!D:D)),5) -> 0
B51: KINETICO VALVE PARTS - METER DISC #2 | C51: Water: Residential (B2C) | D51: 6. Water Treatment | E51: Treatment Spares | F51: 1505 | G51: KINETICO | J51: =CEILING((Query1[[#This Row],[Cost Price ( MYR )]] / (1 - _xlfn.XLOOKUP(Query1[[#This Row],[Business Unit]], Margins!A:A, Margins!C:C))) * (1 - _xlfn.XLOOKUP(Query1[[#This Row],[Business Unit]], Margins!A:A, Margins!D:D)),5) -> 0
B52: KINETICO VALVE PARTS - METER DISC #3 | C52: Water: Residential (B2C) | D52: 6. Water Treatment | E52: Treatment Spares | F52: 1506 | G52: KINETICO | J52: =CEILING((Query1[[#This Row],[Cost Price ( MYR )]] / (1 - _xlfn.XLOOKUP(Query1[[#This Row],[Business Unit]], Margins!A:A, Margins!C:C))) * (1 - _xlfn.XLOOKUP(Query1[[#This Row],[Business Unit]], Margins!A:A, Margins!D:D)),5) -> 0
B53: KINETICO VALVE PARTS - METER DISC #4 | C53: Water: Residential (B2C) | D53: 6. Water Treatment | E53: Treatment Spares | F53: 1507 | G53: KINETICO | J53: =CEILING((Query1[[#This Row],[Cost Price ( MYR )]] / (1 - _xlfn.XLOOKUP(Query1[[#This Row],[Business Unit]], Margins!A:A, Margins!C:C))) * (1 - _xlfn.XLOOKUP(Query1[[#This Row],[Business Unit]], Margins!A:A, Margins!D:D)),5) -> 0
B54: KINETICO VALVE PARTS - METER DISC #5 | C54: Water: Residential (B2C) | D54: 6. Water Treatment | E54: Treatment Spares | F54: 1508 | G54: KINETICO | J54: =CEILING((Query1[[#This Row],[Cost Price ( MYR )]] / (1 - _xlfn.XLOOKUP(Query1[[#This Row],[Business Unit]], Margins!A:A, Margins!C:C))) * (1 - _xlfn.XLOOKUP(Query1[[#This Row],[Business Unit]], Margins!A:A, Margins!D:D)),5) -> 0
A55: 4602503000000448549 | B55: KINETICO, GEAR, TURBINE 10, REGEN | C55: Water: Residential (B2C) | D55: 6. Water Treatment | E55: Treatment Spares | F55: 1671A | G55: KINETICO | H55: 0 | J55: =CEILING((Query1[[#This Row],[Cost Price ( MYR )]] / (1 - _xlfn.XLOOKUP(Query1[[#This Row],[Business Unit]], Margins!A:A, Margins!C:C))) * (1 - _xlfn.XLOOKUP(Query1[[#This Row],[Business Unit]], Margins!A:A, Margins!D:D)),5) -> 0
A56: 4602503000000447383 | B56: MERU MP115 HWM - 3KW WRAPPED PTV, 3/4" | C56: Water: Residential (B2C) | D56: 5. Hot Water Systems | E56: Heaters (Solar/Elec) | F56: COMP-D-000121 | G56: MERU | H56: 0 | J56: =CEILING((Query1[[#This Row],[Cost Price ( MYR )]] / (1 - _xlfn.XLOOKUP(Query1[[#This Row],[Business Unit]], Margins!A:A, Margins!C:C))) * (1 - _xlfn.XLOOKUP(Query1[[#This Row],[Business Unit]], Margins!A:A, Margins!D:D)),5) -> 0
A57: 4602503000013617031 | B57: MERU MP136 HFM - 3 X 3KW SS316 WRAPPED PTV | C57: Water: Residential (B2C) | D57: 5. Hot Water Systems | E57: Heaters (Solar/Elec) | F57: COMP-006077 | G57: MERU | H57: 0 | J57: =CEILING((Query1[[#This Row],[Cost Price ( MYR )]] / (1 - _xlfn.XLOOKUP(Query1[[#This Row],[Business Unit]], Margins!A:A, Margins!C:C))) * (1 - _xlfn.XLOOKUP(Query1[[#This Row],[Business Unit]], Margins!A:A, Margins!D:D)),5) -> 0
A58: 4602503000013726176 | B58: MERU MP136 HWM - 3 X 3KW S316 T2MM WRAPPED PTV | C58: Water: Residential (B2C) | D58: 5. Hot Water Systems | E58: Heaters (Solar/Elec) | F58: COMP-006075 | G58: MERU | H58: 0 | J58: =CEILING((Query1[[#This Row],[Cost Price ( MYR )]] / (1 - _xlfn.XLOOKUP(Query1[[#This Row],[Business Unit]], Margins!A:A, Margins!C:C))) * (1 - _xlfn.XLOOKUP(Query1[[#This Row],[Business Unit]], Margins!A:A, Margins!D:D)),5) -> 0
A59: 4602503000000450784 | B59: MERU MP136 VFM - 3 X 3KW SS316 CARTON PTV | C59: Water: Residential (B2C) | D59: 5. Hot Water Systems | E59: Heaters (Solar/Elec) | F59: COMP-000231-SS316-PTV-3X3KW | G59: MERU | H59: 0 | J59: =CEILING((Query1[[#This Row],[Cost Price ( MYR )]] / (1 - _xlfn.XLOOKUP(Query1[[#This Row],[Business Unit]], Margins!A:A, Margins!C:C))) * (1 - _xlfn.XLOOKUP(Query1[[#This Row],[Business Unit]], Margins!A:A, Margins!D:D)),5) -> 0
A60: 4602503000000097654 | B60: MERU MP25 HCM - 3KW WRAPED BASIC | C60: Water: Residential (B2C) | D60: 5. Hot Water Systems | E60: Heaters (Solar/Elec) | F60: COMP-006200 | G60: MERU | H60: 340.26 | J60: =CEILING((Query1[[#This Row],[Cost Price ( MYR )]] / (1 - _xlfn.XLOOKUP(Query1[[#This Row],[Business Unit]], Margins!A:A, Margins!C:C))) * (1 - _xlfn.XLOOKUP(Query1[[#This Row],[Business Unit]], Margins!A:A, Margins!D:D)),5) -> 610
A61: 4602503000000097335 | B61: MERU MP30 HCM - 3KW WRAPED BASIC | C61: Water: Residential (B2C) | D61: 5. Hot Water Systems | E61: Heaters (Solar/Elec) | F61: COMP-006240 | G61: MERU | H61: 277.96 | J61: =CEILING((Query1[[#This Row],[Cost Price ( MYR )]] / (1 - _xlfn.XLOOKUP(Query1[[#This Row],[Business Unit]], Margins!A:A, Margins!C:C))) * (1 - _xlfn.XLOOKUP(Query1[[#This Row],[Business Unit]], Margins!A:A, Margins!D:D)),5) -> 495
A62: 4602503000000446239 | B62: MERU MP34 HCM - 3KW WRAPED BASIC | C62: Water: Residential (B2C) | D62: 5. Hot Water Systems | E62: Heaters (Solar/Elec) | F62: COMP-006283 | G62: MERU | H62: 314 | J62: =CEILING((Query1[[#This Row],[Cost Price ( MYR )]] / (1 - _xlfn.XLOOKUP(Query1[[#This Row],[Business Unit]], Margins!A:A, Margins!C:C))) * (1 - _xlfn.XLOOKUP(Query1[[#This Row],[Business Unit]], Margins!A:A, Margins!D:D)),5) -> 560
A63: 4602503000000446283 | B63: MERU MP34 HWM-L - 3KW WRAPED BASIC | C63: Water: Residential (B2C) | D63: 5. Hot Water Systems | E63: Heaters (Solar/Elec) | F63: COMP-006285 | G63: MERU | H63: 314 | J63: =CEILING((Query1[[#This Row],[Cost Price ( MYR )]] / (1 - _xlfn.XLOOKUP(Query1[[#This Row],[Business Unit]], Margins!A:A, Margins!C:C))) * (1 - _xlfn.XLOOKUP(Query1[[#This Row],[Business Unit]], Margins!A:A, Margins!D:D)),5) -> 560
A64: 4602503000000446272 | B64: MERU MP34 HWM-R - 3KW WRAPED BASIC | C64: Water: Residential (B2C) | D64: 5. Hot Water Systems | E64: Heaters (Solar/Elec) | F64: COMP-006284 | G64: MERU | H64: 314 | J64: =CEILING((Query1[[#This Row],[Cost Price ( MYR )]] / (1 - _xlfn.XLOOKUP(Query1[[#This Row],[Business Unit]], Margins!A:A, Margins!C:C))) * (1 - _xlfn.XLOOKUP(Query1[[#This Row],[Business Unit]], Margins!A:A, Margins!D:D)),5) -> 560
A65: 4602503000014895038 | B65: MERU MP38 HCM - 3KW WRAPED BASIC | C65: Water: Residential (B2C) | D65: 5. Hot Water Systems | E65: Heaters (Solar/Elec) | F65: COMP-006381 | G65: MERU | H65: 374.3 | J65: =CEILING((Query1[[#This Row],[Cost Price ( MYR )]] / (1 - _xlfn.XLOOKUP(Query1[[#This Row],[Business Unit]], Margins!A:A, Margins!C:C))) * (1 - _xlfn.XLOOKUP(Query1[[#This Row],[Business Unit]], Margins!A:A, Margins!D:D)),5) -> 670
A66: 4602503000021500275 | B66: MERU MP38 HWM-L - 3KW WRAPED BASIC | C66: Water: Residential (B2C) | D66: 5. Hot Water Systems | E66: Heaters (Solar/Elec) | F66: COMP-006389 | G66: MERU | H66: 0 | J66: =CEILING((Query1[[#This Row],[Cost Price ( MYR )]] / (1 - _xlfn.XLOOKUP(Query1[[#This Row],[Business Unit]], Margins!A:A, Margins!C:C))) * (1 - _xlfn.XLOOKUP(Query1[[#This Row],[Business Unit]], Margins!A:A, Margins!D:D)),5) -> 0
... A85: 4602503000000447317 | B85: Summer Solar Collector, CX BlACk, ZnAl | C85: Water: Residential (B2C) | D85: 5. Hot Water Systems | E85: Solar Collectors | F85: COMP-008035 | G85: SUMMER | H85: 529.86 | J85: =CEILING((Query1[[#This Row],[Cost Price ( MYR )]] / (1 - _xlfn.XLOOKUP(Query1[[#This Row],[Business Unit]], Margins!A:A, Margins!C:C))) * (1 - _xlfn.XLOOKUP(Query1[[#This Row],[Business Unit]], Margins!A:A, Margins!D:D)),5) -> 945
B86: HEATING ELEMENT - ELTON | C86: Water: Residential (B2C) | D86: 5. Hot Water Systems | E86: Heating Spares | F86: 3170525 | G86: ELTON | J86: =CEILING((Query1[[#This Row],[Cost Price ( MYR )]] / (1 - _xlfn.XLOOKUP(Query1[[#This Row],[Business Unit]], Margins!A:A, Margins!C:C))) * (1 - _xlfn.XLOOKUP(Query1[[#This Row],[Business Unit]], Margins!A:A, Margins!D:D)),5) -> 0
B87: HEATING ELEMENT - JOVEN | C87: Water: Residential (B2C) | D87: 5. Hot Water Systems | E87: Heating Spares | F87: 3401895 | G87: JOVEN | J87: =CEILING((Query1[[#This Row],[Cost Price ( MYR )]] / (1 - _xlfn.XLOOKUP(Query1[[#This Row],[Business Unit]], Margins!A:A, Margins!C:C))) * (1 - _xlfn.XLOOKUP(Query1[[#This Row],[Business Unit]], Margins!A:A, Margins!D:D)),5) -> 0
B88: HEATING ELEMENT - PECOL | C88: Water: Residential (B2C) | D88: 5. Hot Water Systems | E88: Heating Spares | F88: 3401910 | G88: PECOL | J88: =CEILING((Query1[[#This Row],[Cost Price ( MYR )]] / (1 - _xlfn.XLOOKUP(Query1[[#This Row],[Business Unit]], Margins!A:A, Margins!C:C))) * (1 - _xlfn.XLOOKUP(Query1[[#This Row],[Business Unit]], Margins!A:A, Margins!D:D)),5) -> 0
A89: 4602503000000615235 | B89: HEATING ELEMENT Ã¢â‚¬â€œ 3KW EGO | C89: Water: Residential (B2C) | D89: 5. Hot Water Systems | E89: Heating Spares | F89: S-PART-000311 | H89: 0 | J89: =CEILING((Query1[[#This Row],[Cost Price ( MYR )]] / (1 - _xlfn.XLOOKUP(Query1[[#This Row],[Business Unit]], Margins!A:A, Margins!C:C))) * (1 - _xlfn.XLOOKUP(Query1[[#This Row],[Business Unit]], Margins!A:A, Margins!D:D)),5) -> 0
A90: 4602503000000741075 | B90: HEATING ELEMENT Ã¢â‚¬â€œ INCOLOY 800, RED SEALANT, 3KW/240V, L315MM, STRAIGHT | C90: Water: Residential (B2C) | D90: 5. Hot Water Systems | E90: Heating Spares | F90: PART-000010 | G90: Themowatt | H90: 23.83 | J90: =CEILING((Query1[[#This Row],[Cost Price ( MYR )]] / (1 - _xlfn.XLOOKUP(Query1[[#This Row],[Business Unit]], Margins!A:A, Margins!C:C))) * (1 - _xlfn.XLOOKUP(Query1[[#This Row],[Business Unit]], Margins!A:A, Margins!D:D)),5) -> 45
A91: 4602503000000618510 | B91: HEATING ELEMENT Ã¢â‚¬â€œ INCOLOY 800, WHITE SEALANT, 9KW/415V, L450MM, STRAIGHT | C91: Water: Residential (B2C) | D91: 5. Hot Water Systems | E91: Heating Spares | F91: PART-000003 | G91: Themowatt | H91: 94.29 | J91: =CEILING((Query1[[#This Row],[Cost Price ( MYR )]] / (1 - _xlfn.XLOOKUP(Query1[[#This Row],[Business Unit]], Margins!A:A, Margins!C:C))) * (1 - _xlfn.XLOOKUP(Query1[[#This Row],[Business Unit]], Margins!A:A, Margins!D:D)),5) -> 170
A92: 4602503000000449330 | B92: PART KIT, 180L, DIRECT, CARTON | C92: Water: Residential (B2C) | D92: 5. Hot Water Systems | E92: System Connections | F92: COMP-005624 | G92: SUMMER | H92: 349.08 | J92: =CEILING((Query1[[#This Row],[Cost Price ( MYR )]] / (1 - _xlfn.XLOOKUP(Query1[[#This Row],[Business Unit]], Margins!A:A, Margins!C:C))) * (1 - _xlfn.XLOOKUP(Query1[[#This Row],[Business Unit]], Margins!A:A, Margins!D:D)),5) -> 625
A93: 4602503000000449363 | B93: PARTS KIT J Ã¢â‚¬â€œ 180L / 40G, 3/4Ã¢â‚¬Â, 1 COLLECTOR, SM PACKAGING Ã¢â‚¬â€œ SOLAR: CARTON | C93: Water: Residential (B2C) | D93: 5. Hot Water Systems | E93: System Connections | F93: COMP-005620 | G93: SUMMER | H93: 0 | J93: =CEILING((Query1[[#This Row],[Cost Price ( MYR )]] / (1 - _xlfn.XLOOKUP(Query1[[#This Row],[Business Unit]], Margins!A:A, Margins!C:C))) * (1 - _xlfn.XLOOKUP(Query1[[#This Row],[Business Unit]], Margins!A:A, Margins!D:D)),5) -> 0
A94: 4602503000000446228 | B94: PARTS KIT J Ã¢â‚¬â€œ 300L/66G, 3/4Ã¢â‚¬Â, 2 COLLECTORS, SM PACKAGING Ã¢â‚¬â€œ SOLAR: CARTON | C94: Water: Residential (B2C) | D94: 5. Hot Water Systems | E94: System Connections | F94: COMP-005622 | G94: SUMMER | H94: 0 | J94: =CEILING((Query1[[#This Row],[Cost Price ( MYR )]] / (1 - _xlfn.XLOOKUP(Query1[[#This Row],[Business Unit]], Margins!A:A, Margins!C:C))) * (1 - _xlfn.XLOOKUP(Query1[[#This Row],[Business Unit]], Margins!A:A, Margins!D:D)),5) -> 0
A95: 4602503000000446217 | B95: PARTS KIT S Ã¢â‚¬â€œ 300L / 66G, 3/4Ã¢â‚¬Â, 2 COLLECTORS, SM PACKAGING Ã¢â‚¬â€œ SOLAR: CARTON | C95: Water: Residential (B2C) | D95: 5. Hot Water Systems | E95: System Connections | F95: COMP-005628 | G95: SUMMER | H95: 0 | J95: =CEILING((Query1[[#This Row],[Cost Price ( MYR )]] / (1 - _xlfn.XLOOKUP(Query1[[#This Row],[Business Unit]], Margins!A:A, Margins!C:C))) * (1 - _xlfn.XLOOKUP(Query1[[#This Row],[Business Unit]], Margins!A:A, Margins!D:D)),5) -> 0
A96: 4602503000000449352 | B96: PARTS KIT S Ã¢â‚¬â€œ 450L / 100G, 3/4Ã¢â‚¬Â, 3 COLLECTORS, SM PACKAGING Ã¢â‚¬â€œ SOLAR: CARTON | C96: Water: Residential (B2C) | D96: 5. Hot Water Systems | E96: System Connections | F96: COMP-005632 | G96: SUMMER | H96: 0 | J96: =CEILING((Query1[[#This Row],[Cost Price ( MYR )]] / (1 - _xlfn.XLOOKUP(Query1[[#This Row],[Business Unit]], Margins!A:A, Margins!C:C))) * (1 - _xlfn.XLOOKUP(Query1[[#This Row],[Business Unit]], Margins!A:A, Margins!D:D)),5) -> 0
A97: 4602503000015623002 | B97: THERMOSTAT Ã¢â‚¬â€œ 1P, 240VAC, 50HZ, 30Ã‚Â°C-75Ã‚Â°C | C97: Water: Residential (B2C) | D97: 5. Hot Water Systems | E97: Heating Spares | F97: RAWM-000124 | H97: 123.65 | J97: =CEILING((Query1[[#This Row],[Cost Price ( MYR )]] / (1 - _xlfn.XLOOKUP(Query1[[#This Row],[Business Unit]], Margins!A:A, Margins!C:C))) * (1 - _xlfn.XLOOKUP(Query1[[#This Row],[Business Unit]], Margins!A:A, Margins!D:D)),5) -> 220
A98: 4602503000000620778 | B98: THERMOSTAT Ã¢â‚¬â€œ ECO, 240VAC, 50HZ, 30A, 60Ã‚Â°CÃ¢â‚¬â€œ70Ã‚Â°C, 95Ã‚Â°C | C98: Water: Residential (B2C) | D98: 5. Hot Water Systems | E98: Heating Spares | F98: RAWM-000016 | H98: 32.99 | J98: =CEILING((Query1[[#This Row],[Cost Price ( MYR )]] / (1 - _xlfn.XLOOKUP(Query1[[#This Row],[Business Unit]], Margins!A:A, Margins!C:C))) * (1 - _xlfn.XLOOKUP(Query1[[#This Row],[Business Unit]], Margins!A:A, Margins!D:D)),5) -> 60
A99: 4602503000014992012 | B99: THERMOSTAT Ã¢â‚¬â€œ KP79, SINGLE PHASE, 2KW, 0Ã‚Â°C Ã¢â‚¬â€œ 150Ã‚Â°C | C99: Water: Residential (B2C) | D99: 5. Hot Water Systems | E99: Heating Spares | F99: RAWM-000195 | H99: 370 | J99: =CEILING((Query1[[#This Row],[Cost Price ( MYR )]] / (1 - _xlfn.XLOOKUP(Query1[[#This Row],[Business Unit]], Margins!A:A, Margins!C:C))) * (1 - _xlfn.XLOOKUP(Query1[[#This Row],[Business Unit]], Margins!A:A, Margins!D:D)),5) -> 660
A100: 4602503000000449374 | B100: SUMMER 180L SOLAR WATER HEATER TANK, INDIRECT | C100: Water: Residential (B2C) | D100: 5. Hot Water Systems | E100: Heaters (Solar/Elec) | F100: COMP-005648 | G100: SUMMER | H100: 1055.09 | J100: =CEILING((Query1[[#This Row],[Cost Price ( MYR )]] / (1 - _xlfn.XLOOKUP(Query1[[#This Row],[Business Unit]], Margins!A:A, Margins!C:C))) * (1 - _xlfn.XLOOKUP(Query1[[#This Row],[Business Unit]], Margins!A:A, Margins!D:D)),5) -> 1880
A101: 4602503000004108014 | B101: SUMMER 450L SOLAR WATER HEATER TANK | C101: Water: Residential (B2C) | D101: 5. Hot Water Systems | E101: Heaters (Solar/Elec) | F101: COMP-005672 | G101: SUMMER | H101: 1561.82 | J101: =CEILING((Query1[[#This Row],[Cost Price ( MYR )]] / (1 - _xlfn.XLOOKUP(Query1[[#This Row],[Business Unit]], Margins!A:A, Margins!C:C))) * (1 - _xlfn.XLOOKUP(Query1[[#This Row],[Business Unit]], Margins!A:A, Margins!D:D)),5) -> 2780
A102: 4602503000004837171 | B102: SUMMER SOLAR WATER HEATER TANK, 300L, GVAL | C102: Water: Residential (B2C) | D102: 5. Hot Water Systems | E102: Heaters (Solar/Elec) | F102: COMP-005659 | G102: SUMMER | H102: 1116.44 | J102: =CEILING((Query1[[#This Row],[Cost Price ( MYR )]] / (1 - _xlfn.XLOOKUP(Query1[[#This Row],[Business Unit]], Margins!A:A, Margins!C:C))) * (1 - _xlfn.XLOOKUP(Query1[[#This Row],[Business Unit]], Margins!A:A, Margins!D:D)),5) -> 1990
A103: 4602503000000449319 | B103: SUMMER SOLAR WATER HEATER TANK, 300L, INDIRECT | C103: Water: Residential (B2C) | D103: 5. Hot Water Systems | E103: Heaters (Solar/Elec) | F103: COMP-005663 | G103: SUMMER | H103: 1500.45 | J103: =CEILING((Query1[[#This Row],[Cost Price ( MYR )]] / (1 - _xlfn.XLOOKUP(Query1[[#This Row],[Business Unit]], Margins!A:A, Margins!C:C))) * (1 - _xlfn.XLOOKUP(Query1[[#This Row],[Business Unit]], Margins!A:A, Margins!D:D)),5) -> 2670
A104: 4602503000004549120 | B104: SUMMER SOLAR WATER HEATER TANK, DIRECT 180L, GVAL | C104: Water: Residential (B2C) | D104: 5. Hot Water Systems | E104: Heaters (Solar/Elec) | F104: COMP-005645 | G104: SUMMER | H104: 0 | J104: =CEILING((Query1[[#This Row],[Cost Price ( MYR )]] / (1 - _xlfn.XLOOKUP(Query1[[#This Row],[Business Unit]], Margins!A:A, Margins!C:C))) * (1 - _xlfn.XLOOKUP(Query1[[#This Row],[Business Unit]], Margins!A:A, Margins!D:D)),5) -> 0
A105: 4602503000000617758 | B105: COLLECTOR NUT - BRASS, M30 | C105: Water: Residential (B2C) | D105: 5. Hot Water Systems | E105: Heating Spares | F105: PURC-000160 | H105: 0 | J105: =CEILING((Query1[[#This Row],[Cost Price ( MYR )]] / (1 - _xlfn.XLOOKUP(Query1[[#This Row],[Business Unit]], Margins!A:A, Margins!C:C))) * (1 - _xlfn.XLOOKUP(Query1[[#This Row],[Business Unit]], Margins!A:A, Margins!D:D)),5) -> 0
A106: 4602503000000617659 | B106: COLLECTOR NUT Ã¢â‚¬â€œ BRASS, 3/4Ã¢â‚¬Â, BSP | C106: Water: Residential (B2C) | D106: 5. Hot Water Systems | E106: Heating Spares | F106: PART-000046 | H106: 0 | J106: =CEILING((Query1[[#This Row],[Cost Price ( MYR )]] / (1 - _xlfn.XLOOKUP(Query1[[#This Row],[Business Unit]], Margins!A:A, Margins!C:C))) * (1 - _xlfn.XLOOKUP(Query1[[#This Row],[Business Unit]], Margins!A:A, Margins!D:D)),5) -> 0
A107: 4602503000000615727 | B107: COLLECTOR OLIVE Ã¢â‚¬â€œ BRASS, 3/4Ã¢â‚¬Â X 8MM | C107: Water: Residential (B2C) | D107: 5. Hot Water Systems | E107: Heating Spares | F107: PART-000047 | H107: 0 | J107: =CEILING((Query1[[#This Row],[Cost Price ( MYR )]] / (1 - _xlfn.XLOOKUP(Query1[[#This Row],[Business Unit]], Margins!A:A, Margins!C:C))) * (1 - _xlfn.XLOOKUP(Query1[[#This Row],[Business Unit]], Margins!A:A, Margins!D:D)),5) -> 0
A108: 4602503000000622272 | B108: COLLECTOR OLIVE Ã¢â‚¬â€œ BRASS, OD22MM X L131MM, M30 | C108: Water: Residential (B2C) | D108: 5. Hot Water Systems | E108: Heating Spares | F108: PART-000193 | H108: 0.1 | J108: =CEILING((Query1[[#This Row],[Cost Price ( MYR )]] / (1 - _xlfn.XLOOKUP(Query1[[#This Row],[Business Unit]], Margins!A:A, Margins!C:C))) * (1 - _xlfn.XLOOKUP(Query1[[#This Row],[Business Unit]], Margins!A:A, Margins!D:D)),5) -> 5
A109: 4602503000000620756 | B109: TERMINAL BLOCK @ CONNECTOR | C109: Water: Residential (B2C) | D109: 5. Hot Water Systems | E109: Heating Spares | F109: RAWM-000017 | H109: 0 | J109: =CEILING((Query1[[#This Row],[Cost Price ( MYR )]] / (1 - _xlfn.XLOOKUP(Query1[[#This Row],[Business Unit]], Margins!A:A, Margins!C:C))) * (1 - _xlfn.XLOOKUP(Query1[[#This Row],[Business Unit]], Margins!A:A, Margins!D:D)),5) -> 0
A110: 4602503000000620734 | B110: THEOSTAT AUTO ECO, 240VAC, 50HZ, 30A, 60C 70C | C110: Water: Residential (B2C) | D110: 5. Hot Water Systems | E110: Heating Spares | F110: RAWM-000015 | H110: 34.68 | J110: =CEILING((Query1[[#This Row],[Cost Price ( MYR )]] / (1 - _xlfn.XLOOKUP(Query1[[#This Row],[Business Unit]], Margins!A:A, Margins!C:C))) * (1 - _xlfn.XLOOKUP(Query1[[#This Row],[Business Unit]], Margins!A:A, Margins!D:D)),5) -> 65
A111: 4602503000000190085 | B111: Cartridge Kinetico FC-550 NanofACt Cartridge | C111: Water: Recurring Care (Opex) | D111: 7. Water Consumables | E111: Cartridges | F111: 100-1002 | G111: KINETICO | H111: 0 | J111: =CEILING((Query1[[#This Row],[Cost Price ( MYR )]] / (1 - _xlfn.XLOOKUP(Query1[[#This Row],[Business Unit]], Margins!A:A, Margins!C:C))) * (1 - _xlfn.XLOOKUP(Query1[[#This Row],[Business Unit]], Margins!A:A, Margins!D:D)),5) -> 0
B112: KINETICO CARTRIDGE SELECTO QCM-350+ | C112: Water: Recurring Care (Opex) | D112: 7. Water Consumables | E112: Cartridges | F112: 16508 | G112: KINETICO | J112: =CEILING((Query1[[#This Row],[Cost Price ( MYR )]] / (1 - _xlfn.XLOOKUP(Query1[[#This Row],[Business Unit]], Margins!A:A, Margins!C:C))) * (1 - _xlfn.XLOOKUP(Query1[[#This Row],[Business Unit]], Margins!A:A, Margins!D:D)),5) -> 0
A113: 4602503000000448428 | B113: KINETICO CARTRIDGE K5 MEMBRANE GREEN | C113: Water: Recurring Care (Opex) | D113: 7. Water Consumables | E113: Cartridges | F113: 12752B | G113: KINETICO | H113: 233.14 | J113: =CEILING((Query1[[#This Row],[Cost Price ( MYR )]] / (1 - _xlfn.XLOOKUP(Query1[[#This Row],[Business Unit]], Margins!A:A, Margins!C:C))) * (1 - _xlfn.XLOOKUP(Query1[[#This Row],[Business Unit]], Margins!A:A, Margins!D:D)),5) -> 520
A114: 4602503000000448439 | B114: KINETICO CARTRIDGE K5/A200 MAC T&O (12673) | C114: Water: Recurring Care (Opex) | D114: 7. Water Consumables | E114: Cartridges | F114: 9306B | G114: KINETICO | H114: 100.63 | J114: =CEILING((Query1[[#This Row],[Cost Price ( MYR )]] / (1 - _xlfn.XLOOKUP(Query1[[#This Row],[Business Unit]], Margins!A:A, Margins!C:C))) * (1 - _xlfn.XLOOKUP(Query1[[#This Row],[Business Unit]], Margins!A:A, Margins!D:D)),5) -> 225
B115: KINETICO CARTRIDGE SELECTO SMF IC600 10" | C115: Water: Recurring Care (Opex) | D115: 7. Water Consumables | E115: Cartridges | F115: 16647 | G115: KINETICO | J115: =CEILING((Query1[[#This Row],[Cost Price ( MYR )]] / (1 - _xlfn.XLOOKUP(Query1[[#This Row],[Business Unit]], Margins!A:A, Margins!C:C))) * (1 - _xlfn.XLOOKUP(Query1[[#This Row],[Business Unit]], Margins!A:A, Margins!D:D)),5) -> 0
B116: KINETICO CARTRIDGE SELECTO SMF IC614 14" | C116: Water: Recurring Care (Opex) | D116: 7. Water Consumables | E116: Cartridges | F116: 16648 | G116: KINETICO | J116: =CEILING((Query1[[#This Row],[Cost Price ( MYR )]] / (1 - _xlfn.XLOOKUP(Query1[[#This Row],[Business Unit]], Margins!A:A, Margins!C:C))) * (1 - _xlfn.XLOOKUP(Query1[[#This Row],[Business Unit]], Margins!A:A, Margins!D:D)),5) -> 0
B117: KINETICO CARTRIDGE TF75 MEMBRANE | C117: Water: Recurring Care (Opex) | D117: 7. Water Consumables | E117: Cartridges | F117: 10501 | G117: KINETICO | J117: =CEILING((Query1[[#This Row],[Cost Price ( MYR )]] / (1 - _xlfn.XLOOKUP(Query1[[#This Row],[Business Unit]], Margins!A:A, Margins!C:C))) * (1 - _xlfn.XLOOKUP(Query1[[#This Row],[Business Unit]], Margins!A:A, Margins!D:D)),5) -> 0
A118: 4602503000000190074 | B118: KINETICO Carbon Cartridge 8Ã¢â‚¬Â FC-550 | C118: Water: Recurring Care (Opex) | D118: 7. Water Consumables | E118: Cartridges | F118: 100-1001 | G118: KINETICO | H118: 0 | J118: =CEILING((Query1[[#This Row],[Cost Price ( MYR )]] / (1 - _xlfn.XLOOKUP(Query1[[#This Row],[Business Unit]], Margins!A:A, Margins!C:C))) * (1 - _xlfn.XLOOKUP(Query1[[#This Row],[Business Unit]], Margins!A:A, Margins!D:D)),5) -> 0
A119: 4602503000000446690 | B119: KINETICO MACH Prefilter Cartridge 10Ã¢â‚¬Â 5Micron Reusable | C119: Water: Recurring Care (Opex) | D119: 7. Water Consumables | E119: Cartridges | F119: 11827A | G119: KINETICO | H119: 1094.67 | J119: =CEILING((Query1[[#This Row],[Cost Price ( MYR )]] / (1 - _xlfn.XLOOKUP(Query1[[#This Row],[Business Unit]], Margins!A:A, Margins!C:C))) * (1 - _xlfn.XLOOKUP(Query1[[#This Row],[Business Unit]], Margins!A:A, Margins!D:D)),5) -> 2435
...

Sheet Composite SKUs
A1: Item ID | B1: Item SKU | C1: Name | D1: Status | E1: List Price
A2: 4.602503e+18 | B2: D-IKPVKL406P-1 | C2: D-PV Install Kit Klip-Lok 406 Portrait 1/R | D2: Active | E2: =_xlfn.XLOOKUP(Query2[[#This Row],[Item ID]],[1]PASTE_ZOHO_HERE!$A$2:$A$32,[1]PASTE_ZOHO_HERE!$H$2:$H$32) -> 240
A3: 4.602503e+18 | B3: IKPVKL406L-8 | C3: PV INSTALL KIT KLIP-LOK 406 LANDSCAPE 8/R | D3: Active | E3: =_xlfn.XLOOKUP(Query2[[#This Row],[Item ID]],[1]PASTE_ZOHO_HERE!$A$2:$A$32,[1]PASTE_ZOHO_HERE!$H$2:$H$32) -> 1290
A4: 4.602503e+18 | B4: D-IKPVKL700P-7 | C4: D-PV Install Kit Klip-Lok 700 Portrait 7/R | D4: Active | E4: =_xlfn.XLOOKUP(Query2[[#This Row],[Item ID]],[1]PASTE_ZOHO_HERE!$A$2:$A$32,[1]PASTE_ZOHO_HERE!$H$2:$H$32) -> 1090
A5: 4.602503e+18 | B5: IKPVSL-10 | C5: PV Install Kit Shingle Landscape 10/R | D5: Active | E5: =_xlfn.XLOOKUP(Query2[[#This Row],[Item ID]],[1]PASTE_ZOHO_HERE!$A$2:$A$32,[1]PASTE_ZOHO_HERE!$H$2:$H$32) -> 1220
A6: 4.602503e+18 | B6: IKPVSSP-10 | C6: PV INSTALL KIT STANDING SEAM PORTRAIT 10/R | D6: Active | E6: =_xlfn.XLOOKUP(Query2[[#This Row],[Item ID]],[1]PASTE_ZOHO_HERE!$A$2:$A$32,[1]PASTE_ZOHO_HERE!$H$2:$H$32) -> 1820
A7: 4.602503e+18 | B7: D-IKPVLBP-1 | C7: D-PV Install Kit Concrete Low Portrait 1/R | D7: Active | E7: =_xlfn.XLOOKUP(Query2[[#This Row],[Item ID]],[1]PASTE_ZOHO_HERE!$A$2:$A$32,[1]PASTE_ZOHO_HERE!$H$2:$H$32) -> 400
A8: 4.602503e+18 | B8: D-IKPVE-11 | C8: D-PV Electrical Install Kit, 1 Phase, String, 1-2 Floor | D8: Active | E8: =_xlfn.XLOOKUP(Query2[[#This Row],[Item ID]],[1]PASTE_ZOHO_HERE!$A$2:$A$32,[1]PASTE_ZOHO_HERE!$H$2:$H$32) -> 10825
A9: 4.602503e+18 | B9: T-514 | C9: Stump | D9: Active | E9: =_xlfn.XLOOKUP(Query2[[#This Row],[Item ID]],[1]PASTE_ZOHO_HERE!$A$2:$A$32,[1]PASTE_ZOHO_HERE!$H$2:$H$32) -> 0
A10: 4.602503e+18 | B10: D-AP-3P-2K | C10: D-APSYSTEMS 3P 2Acc Kit | D10: Active | E10: =_xlfn.XLOOKUP(Query2[[#This Row],[Item ID]],[1]PASTE_ZOHO_HERE!$A$2:$A$32,[1]PASTE_ZOHO_HERE!$H$2:$H$32) -> 1000
A11: 4.602503e+18 | B11: D-SOL-030 | C11: D-SUMMER 400SX Solar Hot Water Complete System | D11: Active | E11: =_xlfn.XLOOKUP(Query2[[#This Row],[Item ID]],[1]PASTE_ZOHO_HERE!$A$2:$A$32,[1]PASTE_ZOHO_HERE!$H$2:$H$32) -> 170
A12: 4.602503e+18 | B12: AP-1P-2K | C12: APSYSTEM 1P 2ACC KIT | D12: Active | E12: =_xlfn.XLOOKUP(Query2[[#This Row],[Item ID]],[1]PASTE_ZOHO_HERE!$A$2:$A$32,[1]PASTE_ZOHO_HERE!$H$2:$H$32) -> 1055
A13: 4.602503e+18 | B13: Testing Code 1 | C13: Testing Kit item | D13: Active | E13: =_xlfn.XLOOKUP(Query2[[#This Row],[Item ID]],[1]PASTE_ZOHO_HERE!$A$2:$A$32,[1]PASTE_ZOHO_HERE!$H$2:$H$32) -> 0
... A32: 4.602503e+18 | B32: 300CVFSYS | C32: SUMMER 300CVF FORCED CIRCULATION SYSTEM | D32: Active | E32: =_xlfn.XLOOKUP(Query2[[#This Row],[Item ID]],[1]PASTE_ZOHO_HERE!$A$2:$A$32,[1]PASTE_ZOHO_HERE!$H$2:$H$32) -> 945

Sheet Margins
A1: TEAM | B1: Ratio | C1: Margin | D1: List | E1: Discount (Green) | F1: Discount (Amber) | G1: Discount (Red) | H1: Dealer | I1: GP (Green) | J1: GP (Amber) | K1: GP (Red) | L1: Dealer GP
A2: Services: Labour & Fees | B2: 20 | C2: 0.9 | D2: 0.333 | E2: 0.4 | F2: 0.45 | G2: 0.51 | I2: =1 - ((1 - $C$2) / (1 - E2)) -> 0.83333333 | J2: =1 - ((1 - $C$2) / (1 - F2)) -> 0.81818182 | K2: =1 - ((1 - $C$2) / (1 - G2)) -> 0.79591837
A3: Solar: Residential (B2C) | B3: 28 | C3: 0.625 | D3: 0.333 | E3: 0.4 | F3: 0.45 | G3: 0.51 | H3: 0.56 | I3: =1 - ((1 - $C$3) / (1 - E3)) -> 0.375 | J3: =1 - ((1 - $C$3) / (1 - F3)) -> 0.31818182 | K3: =1 - ((1 - $C$3) / (1 - G3)) -> 0.23469388 | L3: =1 - ((1 - $C$3) / (1 - H3)) -> 0.14772727
A4: Solar: Commercial (C&I) | B4: 10 | C4: 0.625 | D4: 0.333 | E4: 0.4 | F4: 0.45 | G4: 0.51 | I4: =1 - ((1 -$C$4) / (1 - E4)) -> 0.375 | J4: =1 - ((1 -$C$4) / (1 - F4)) -> 0.31818182 | K4: =1 - ((1 -$C$4) / (1 - G4)) -> 0.23469388
A5: Solar: Infrastructure | B5: 5 | C5: 0.75 | D5: 0.333 | E5: 0.4 | F5: 0.45 | G5: 0.51 | I5: =1 - ((1 - $C$5) / (1 - E5)) -> 0.58333333 | J5: =1 - ((1 - $C$5) / (1 - F5)) -> 0.54545455 | K5: =1 - ((1 - $C$5) / (1 - G5)) -> 0.48979592
A6: Water: Residential (B2C) | B6: 5 | C6: 0.625 | D6: 0.333 | E6: 0.4 | F6: 0.45 | G6: 0.51 | H6: 0.56 | I6: =1 - ((1 - $C$6) / (1 - E6)) -> 0.375 | J6: =1 - ((1 - $C$6) / (1 - F6)) -> 0.31818182 | K6: =1 - ((1 - $C$6) / (1 - G6)) -> 0.23469388 | L6: =1 - ((1 - $C$6) / (1 - H6)) -> 0.14772727
A7: Water: Commercial (C&I) | B7: 15 | C7: 0.625 | D7: 0.333 | E7: 0.4 | F7: 0.45 | G7: 0.51 | I7: =1 - ((1 - $C$7) / (1 - E7)) -> 0.375 | J7: =1 - ((1 - $C$7) / (1 - F7)) -> 0.31818182 | K7: =1 - ((1 - $C$7) / (1 - G7)) -> 0.23469388
A8: Water: Recurring Care (Opex) | B8: 5 | C8: 0.7 | D8: 0.333 | E8: 0.4 | F8: 0.45 | G8: 0.51 | I8: =1 - ((1 - $C$8) / (1 - E8)) -> 0.5 | J8: =1 - ((1 - $C$8) / (1 - F8)) -> 0.45454545 | K8: =1 - ((1 - $C$8) / (1 - G8)) -> 0.3877551
A9: Water: Infrastructure | B9: 2 | C9: 0.75 | D9: 0.333 | E9: 0.4 | F9: 0.45 | G9: 0.51 | I9: =1 - ((1 - $C$9) / (1 - E9)) -> 0.58333333 | J9: =1 - ((1 - $C$9) / (1 - F9)) -> 0.54545455 | K9: =1 - ((1 - $C$9) / (1 - G9)) -> 0.48979592
B10: =SUM(B2:B9) -> 90 | C10: =AVERAGE(C2:C9) -> 0.7 | I10: =AVERAGE(I2:I9) -> 0.5 | J10: =AVERAGE(J2:J9) -> 0.45454545 | K10: =AVERAGE(K2:K9) -> 0.3877551
A12: CONTRACT
A13: Services: Equipment Rental | C13: 0.51 | D13: 0.333 | E13: 0.4 | F13: 0.45 | G13: 0.51 | I13: =1 - ((1 - $C$13) / (1 - E13)) -> 0.18333333 | J13: =1 - ((1 - $C$13) / (1 - F13)) -> 0.10909091 | K13: =1 - ((1 - $C$13) / (1 - G13)) -> 0
